{
    "1": {
        "6 6 2897 434": [
            "臺灣省                                                 選舉公報",
            "彰化縣選舉委員會 編印",
            "臺灣省彰化縣員林鎮第十七屆鎮長選舉、員林鎮民代表會第二十屆代表第一選區選舉、員林鎮第二十屆里長選舉，經定於中華民國 103 年 11 月 29",
            "日 ( 星期六 ) 上午 8 時起至下午 4 時止舉行投票。茲依公職人員選舉罷免法第四十七條規定，將候選人所填之政見及個人資料刊登如下，候選人個人資料",
            "彰化縣員林鎮民代表會第二十屆代表選舉第一選舉區",
            "彰化縣員林鎮第二十屆里長選舉"
        ],
        "6 438 2897 678": [
            "係依據候選人所填列資料刊登，如有不實，由候選人自行負責。",
            "臺灣省彰化縣員林鎮第十七屆鎮長選舉候選人"
        ],
        "6 682 2897 747": [
            "相      片 學    歷 經      歷 政      見",
            "相      片 學    歷 經      歷 政      見"
        ],
        "6 751 68 896": [

        ],
        "69 751 314 896": [

        ],
        "316 751 360 896": [

        ],
        "361 751 405 896": [

        ],
        "406 751 450 896": [

        ],
        "452 751 496 896": [

        ],
        "497 751 541 896": [

        ],
        "542 751 717 896": [

        ],
        "718 751 978 896": [

        ],
        "979 751 1439 896": [
            "一、重視里長反映民意，並儘速協助解決，建立優",
            "質及和諧的生活環境。",
            "二、簡化急難救助及馬上關懷申請程序，提供弱勢",
            "者迅速的援助。",
            "三、檢討市區內閒置土地，規劃小型停車場，解決",
            "市區內停車空間不足問題。"
        ],
        "1459 751 1524 896": [

        ],
        "1526 751 1771 896": [

        ],
        "1772 751 1816 896": [

        ],
        "1818 751 1862 896": [

        ],
        "1863 751 1907 896": [

        ],
        "1909 751 1952 896": [

        ],
        "1954 751 1998 896": [

        ],
        "1999 751 2174 896": [

        ],
        "2175 751 2434 896": [

        ],
        "2436 751 2897 896": [
            "秉持廉能、效率、便民、勤政施政理念，建構公所",
            "優質服務環境及設備，提供完善公共設施，舒適便",
            "捷交通網，綠美化市容環境、促進文教工商農業觀",
            "光發展，建設東區樂活花園、西區藝術廊道、南區",
            "運動公園、北區商圈美食，邁向最棒的城市幸福「"
        ],
        "6 898 68 1604": [

        ],
        "69 898 314 1604": [
            "臺灣省彰化縣員林鎮民代表會第二十屆代表選舉第一選舉區候選人",
            "1"
        ],
        "316 898 360 1604": [

        ],
        "361 898 405 1604": [

        ],
        "406 898 450 1604": [

        ],
        "452 898 496 1604": [
            "55",
            "18"
        ],
        "497 898 541 1604": [

        ],
        "542 898 717 1604": [
            "1. 文化大學史",
            "學研究所碩",
            "士畢業",
            "2. 文化大學史",
            "學系畢業",
            "3. 臺中女中畢",
            "業",
            "4. 南投縣名間",
            "國中畢業",
            "5. 南投縣僑興",
            "國小畢業"
        ],
        "718 898 978 1604": [
            "1.國立空中大學講師。",
            "2.立法委員魏明谷國會助",
            "理。",
            "3.大葉大學兼任講師。",
            "4.民主進步黨第10～16屆",
            "全國黨員代表。",
            "5.彰化縣南投同鄉會總幹",
            "事。",
            "6.2010－2011年員林百果",
            "山獅子會會長。",
            "7.第16、17屆彰化縣議員",
            "。"
        ],
        "979 898 1439 1604": [
            "四、妥善規劃「員林鐵路高架橋下」廊道，提供鎮",
            "民停車、運動休閒、購物的空間。",
            "五、爭取經費，儘速解決「員林１８４公頃市地重",
            "建工程」所衍生的新、舊市區道路、水溝等界",
            "面無法銜接的問題，保障地主的權益。",
            "六、尋求產官學合作，積極開發「自行車產業園區",
            "」，帶動員林百果山風景特定區觀光發展。",
            "七、於舊縣立醫院現址，爭取設置福佬客文化紀念",
            "館，提供更優質的閱讀‘展覽等藝文空間。",
            "八、爭取設置兼具防災與運動休閒的多功能防災公",
            "園，颱風豪雨季時，可作為吸納雨水的滯洪池",
            "，平日則是運動休閒的公園。",
            "九、妥善規劃青山綠水環鎮自行車廊道，倡導綠能",
            "低碳與環保，營造綠色健康生活圈。",
            "十、透過產銷班推廣安全無毒產業；補助小型農機",
            "具，減輕農村人力不足問題。",
            "十一、發展地方特產及飲食文化，結合觀光旅遊，",
            "行銷地方產業，營造魅力城市。",
            "十二、爭取山腳路外環道，由林厝匝道北接花壇東",
            "外環，以及台76線由埔心匝道連結東北里山",
            "腳路聯絡道，促進員林發展。",
            "十三、充實鎮托軟硬體設備，讓幼童安心學習成長",
            "。",
            "十四、爭取員林改制為市。"
        ],
        "1459 898 1524 1604": [

        ],
        "1526 898 1771 1604": [
            "2"
        ],
        "1772 898 1816 1604": [

        ],
        "1818 898 1862 1604": [

        ],
        "1863 898 1907 1604": [

        ],
        "1909 898 1952 1604": [
            "54",
            "3",
            "2"
        ],
        "1954 898 1998 1604": [

        ],
        "1999 898 2174 1604": [
            "中州技術學院",
            "( 二專 ) 副學士",
            "畢業"
        ],
        "2175 898 2434 1604": [
            "第十六屆員林鎮鎮長。",
            "第十五、十六、十七屆彰",
            "化縣議員。",
            "太平國際同濟會創會長。",
            "錦龍獅子會理事。",
            "大同國中家長會副會長。",
            "員林農工家長委員。",
            "中州校友會總會理事。",
            "佛光山會會員。",
            "妙惠慈善會顧問。",
            "員林桌球委員會主委。",
            "大葉大學碩士學分班。"
        ],
        "2436 898 2897 1604": [
            "一、員林都市計畫第四次通盤檢討，都市更新融和",
            "新舊市區發展，建置容積移轉資訊平台。",
            "二、鐵路高架橋下空間規劃觀光夜市、生鮮市集、",
            "文化創意產業、里民活動及停車空間、雨水下",
            "水道排水系統。",
            "三、184公頃城市再造，爭取彰南運動中心、主題公",
            "園建設、延伸自行車Ubike系統。",
            "四、關懷重大罕見傷病家庭，生活醫療年節慰問撫",
            "助。補助農民購買肥料每年每公頃3000元。",
            "五、開源節流節能減碳增裕財政，活化鎮有地及撥",
            "用公有地；增進公有市場、停車場經濟效益；",
            "幼兒園增班社區班公辦民營；推動e化圖書館；",
            "增建里民社區集會場所；增加老人日托據點。",
            "六、爭取台７６線員林北側聯絡道新闢道路工程，",
            "有效疏解交通瓶頸。",
            "七、爭取打造百果山兒童樂園、普及青少年場所免",
            "費上網熱區、新建客家文化展演舞台。",
            "八、爭取石笱排水整治及堤岸道路改善，改善中山",
            "路二段、過溝排水、大村排水、百果山巷道等",
            "排水。",
            "九、爭取大型藝術展覽及運動場地。",
            "十、爭取員林鎮衛生所遷建。"
        ],
        "6 1608 2897 1672": [
            "相      片 學    歷 經      歷 政      見",
            "相      片 學    歷 經      歷 政      見"
        ],
        "6 1676 68 1820": [

        ],
        "69 1676 314 1820": [

        ],
        "316 1676 360 1820": [

        ],
        "361 1676 405 1820": [

        ],
        "406 1676 450 1820": [

        ],
        "452 1676 496 1820": [

        ],
        "497 1676 541 1820": [

        ],
        "542 1676 717 1820": [

        ],
        "718 1676 978 1820": [
            "東昇超市負責人、彰化縣酒"
        ],
        "979 1676 1439 1820": [
            "一、監督、推展鎮政、以民意為依歸，反映民意、專心服",
            "務。",
            "二、爭取建設地方需要，服務地方，誠心為鎮民服務、爭",
            "取鎮民福利、多方爭取經費。",
            "三、加強弱勢群族、新住民，公益、福利爭取，並建立各",
            "項溝通與福利平台。"
        ],
        "1459 1676 1524 1820": [

        ],
        "1526 1676 1771 1820": [

        ],
        "1772 1676 1816 1820": [

        ],
        "1818 1676 1862 1820": [

        ],
        "1863 1676 1907 1820": [

        ],
        "1909 1676 1952 1820": [

        ],
        "1954 1676 1998 1820": [

        ],
        "1999 1676 2174 1820": [

        ],
        "2175 1676 2434 1820": [
            "彰化縣議員游振雄助理",
            "彰化縣勞工家庭關懷協會"
        ],
        "2436 1676 2897 1820": [
            "一、本人電話全天候接聽服務、積極爭取地方建設",
            "、民眾福祉，加強改善道路交通、山區防洪及",
            "積水、排水等問題，以保障民眾生命財產的安",
            "全。"
        ],
        "6 1822 68 2302": [

        ],
        "69 1822 314 2302": [
            "1"
        ],
        "316 1822 360 2302": [

        ],
        "361 1822 405 2302": [

        ],
        "406 1822 450 2302": [

        ],
        "452 1822 496 2302": [
            "55",
            "4",
            "14"
        ],
        "497 1822 541 2302": [

        ],
        "542 1822 717 2302": [
            "嘉義神州高級",
            "中學畢業",
            "青山國民小學"
        ],
        "718 1822 978 2302": [
            "類公會理事長、員林鎮振興",
            "社區理事長、員林鎮出水社",
            "區常務監事、員林鎮青山國",
            "小家長委員會會長、臺灣省",
            "酒類公會理事、天化慈善會",
            "顧問、1996年員林鎮青年楷",
            "模、2004年彰化縣商業總會",
            "優良商人、2012年彰化縣商",
            "業總會優良理事長"
        ],
        "979 1822 1439 2302": [
            "四、督促公所照顧農民權益，注重農民福利，增加農民所",
            "得。",
            "五、推廣精緻農業，促進產業升級，提升市場競爭力。",
            "六、督促公所加強照顧貧病、殘障及低收入戶等弱勢之福",
            "利。",
            "七、推動社會福利服務，關懷弱勢群族、老人及幼兒等福",
            "利。",
            "八、加強與推廣社福醫療。",
            "九、員林鎮內各道路、安全設施、路燈、排水溝改善與整",
            "修。",
            "十、全力爭取各村里集會所、活動中心完成，全力架構鎮",
            "民洽公、休閒場所，並力促各里通訊、店家服務工作",
            "推廣。",
            "十一、推動社區發展，加強社區聯誼，促進地方和諧與進",
            "步。",
            "十二、全力推動員林鎮休閒觀光產業，帶動地方繁榮。",
            "一、爭取雨水下水道（",
            "湶",
            "州巷至大饒路）路段，將",
            "雨水導入員大排，改善山腳路二段（青山國小"
        ],
        "1459 1822 1524 2302": [

        ],
        "1526 1822 1771 2302": [
            "5"
        ],
        "1772 1822 1816 2302": [

        ],
        "1818 1822 1862 2302": [

        ],
        "1863 1822 1907 2302": [

        ],
        "1909 1822 1952 2302": [
            "58",
            "4",
            "30"
        ],
        "1954 1822 1998 2302": [

        ],
        "1999 1822 2174 2302": [
            "中州技術學院",
            "行銷與流通管",
            "理系畢業"
        ],
        "2175 1822 2434 2302": [
            "理事長",
            "員林鎮林厝社區發展協會",
            "監事",
            "曾任員林鎮社區發展協會",
            "總幹事",
            "曾任彰化縣善德社會關懷",
            "協進會總幹事",
            "曾任青山國小家長委員會",
            "常務委員",
            "第一產物保險公司營業員",
            "第19屆員林鎮民代表",
            "彰化縣議員江瑞演服務處",
            "主任"
        ],
        "2436 1822 2897 2302": [
            "二、爭取青山及東山國小設置幼兒班，讓學區學童",
            "能依學區就讀，提早適應升小學後的校園生活",
            "環境。",
            "三、爭取規劃員林鎮東區八卦山脈各景點之觀光建",
            "設，推動蜜餞產業合作，建立蜜餞觀光工廠，",
            "設置銷售攤位，行銷東區產業、行銷員林，創",
            "造地方商機與繁榮。",
            "四、爭取輔導推動社區整體營造，美化環境，關心",
            "弱勢家庭及老人，共創和諧且富有人情味的好",
            "地方。",
            "五、傾聽民意，全力以民意為服務重點，以最熱忱",
            "的行動力，最專業的服務來回報民眾的支持。"
        ],
        "6 2304 68 2784": [

        ],
        "69 2304 314 2784": [
            "2"
        ],
        "316 2304 360 2784": [

        ],
        "361 2304 405 2784": [

        ],
        "406 2304 450 2784": [

        ],
        "452 2304 496 2784": [
            "62",
            "5",
            "24"
        ],
        "497 2304 541 2784": [

        ],
        "542 2304 717 2784": [
            "畢業",
            "明倫國民中學",
            "畢業",
            "國立永靖高級",
            "工業職業學校",
            "畢業",
            "私立萬能科技",
            "大學（二專部",
            "）畢業"
        ],
        "718 2304 978 2784": [
            "員林鎮兵役委員",
            "員林鎮調解委員",
            "立法委員蕭景田助理",
            "員林鎮第16、17屆鎮民代",
            "表",
            "員林鎮民代表會第18、19",
            "屆副主席"
        ],
        "979 2304 1439 2784": [
            "至大慶商工）淹水問題。",
            "二、爭取東北里小嶺頂設置為自行車休閒觀光園區",
            "。",
            "三、爭取百果山遊樂區增設各項遊樂設施。",
            "四、爭取員林鎮山腳路一段與二段（林厝派出所前",
            "）、整體通盤檢討規劃拓寬、以解決交通問題",
            "。",
            "五、爭取東區各里公共設施，改善、維修等工作。",
            "六、協助弱勢族群爭取社會福利。",
            "七、反映鎮民各項陳情案件。"
        ],
        "1459 2304 1524 2784": [

        ],
        "1526 2304 1771 2784": [
            "6"
        ],
        "1772 2304 1816 2784": [

        ],
        "1818 2304 1862 2784": [

        ],
        "1863 2304 1907 2784": [

        ],
        "1909 2304 1952 2784": [
            "39",
            "1",
            "15"
        ],
        "1954 2304 1998 2784": [

        ],
        "1999 2304 2174 2784": [
            "彰化高商畢業"
        ],
        "2175 2304 2434 2784": [
            "員林浮圳社區長壽俱樂部",
            "會長",
            "絡力馨經穴養生志工隊執",
            "行長",
            "台化公司勞資會議代表",
            "台化公司福利委員",
            "台化公司工會代表．理事",
            "彰化縣模範勞工",
            "逢甲大學資訊工程學系培",
            "基語言講習班結業"
        ],
        "2436 2304 2897 2784": [
            "一、推動員林升市早日實現。",
            "二、促進百果山風華再現繁榮地方。",
            "三、監督鎮政、落實預算執行。",
            "四、堅守鎮民與公所溝通橋樑。"
        ],
        "6 2786 68 3266": [

        ],
        "69 2786 314 3266": [
            "3"
        ],
        "316 2786 360 3266": [

        ],
        "361 2786 405 3266": [

        ],
        "406 2786 450 3266": [

        ],
        "452 2786 496 3266": [
            "58",
            "9",
            "11"
        ],
        "497 2786 541 3266": [

        ],
        "542 2786 717 3266": [
            "曉陽商工肄"
        ],
        "718 2786 978 3266": [
            "第十九屆員林鎮民代表",
            "第七屆員林鎮浮圳社區發",
            "展協會理事長"
        ],
        "979 2786 1439 3266": [
            "為鄉親服務，為地方建設。"
        ],
        "1459 2786 1524 3266": [

        ],
        "1526 2786 1771 3266": [
            "7"
        ],
        "1772 2786 1816 3266": [

        ],
        "1818 2786 1862 3266": [

        ],
        "1863 2786 1907 3266": [

        ],
        "1909 2786 1952 3266": [
            "39",
            "12",
            "26"
        ],
        "1954 2786 1998 3266": [

        ],
        "1999 2786 2174 3266": [
            "埔心初級中學",
            "畢業"
        ],
        "2175 2786 2434 3266": [
            "專職第15、17、18、19屆振",
            "興里里長、前振興社區發展",
            "協會總幹事、現任里長"
        ],
        "2436 2786 2897 3266": [
            "不分黨派，不加入政黨政治。",
            "用心爭取區內各項大小建設。",
            "東區里民的利益為優先，服務，服務再服務。",
            "一、均衡地方區域發展，改善東區建設，並維護東",
            "區自然生態環境，提昇生活品質，加強守望相",
            "助，維護治安。",
            "二、協助弱勢團體及婦女爭取權益，並照顧單親家"
        ],
        "6 3267 68 3746": [

        ],
        "69 3267 314 3746": [
            "4",
            "鎮民代表選舉區之劃分及應選出名額如下：",
            "選舉區別 所轄村里名稱 應選出名額 備註"
        ],
        "316 3267 360 3746": [

        ],
        "361 3267 405 3746": [

        ],
        "406 3267 450 3746": [

        ],
        "452 3267 496 3746": [
            "58",
            "1",
            "24"
        ],
        "497 3267 541 3746": [

        ],
        "542 3267 717 3746": [
            "國中肄業"
        ],
        "718 3267 978 3746": [
            "現任彰化縣弱勢者關懷協",
            "會創會長、彰化縣南瑤宮",
            "老二媽會、北角董事國際",
            "同濟會百果山會現任會長",
            "、員林鎮中東里福德宮監",
            "務委員、大甲媽祖員林分",
            "會副會長、東山國小家長",
            "會顧問團首席副團長、員",
            "東國小家長會顧問"
        ],
        "979 3267 1439 3746": [
            "一、關懷弱勢族群、獨居老人、低收入戶。",
            "二、爭取社區建設福利",
            "三、關懷婦女、兒童爭取福利。",
            "四、關懷新住民爭取福利。"
        ],
        "1459 3267 1524 3746": [

        ],
        "1526 3267 1771 3746": [
            "8"
        ],
        "1772 3267 1816 3746": [

        ],
        "1818 3267 1862 3746": [

        ],
        "1863 3267 1907 3746": [

        ],
        "1909 3267 1952 3746": [
            "42",
            "2",
            "23"
        ],
        "1954 3267 1998 3746": [

        ],
        "1999 3267 2174 3746": [
            "國小畢業"
        ],
        "2175 3267 2434 3746": [
            "1.員林鎮民代表會第18屆",
            "代表",
            "2.員林鎮婦聯會常務委員",
            "3.員林鎮代天宮顧問",
            "4.彰化南瑤宮老二媽會顧",
            "問"
        ],
        "2436 3267 2897 3746": [
            "三、關懷老人安養問題及加強保護幼兒安全及福利",
            "，並促進社區發展協會永續經營，提昇軟硬體",
            "之優質環境。",
            "四、督促鎮政，施政應以民意為依歸，增進民眾福",
            "祉為目的。",
            "五、加強鎮政建設，開發東區商業生機，促進東區",
            "發展繁榮而努力。",
            "六、力促鎮公所做好山區防洪計畫，加強水土保持",
            "，改善排水系統，確保人民生命財產之安全。",
            "七、善盡民代職責，為民喉舌，提案鎮民所建議之",
            "地方建設之軟硬體方案，增進東區民眾福利為",
            "目的。"
        ],
        "6 3750 2897 4176": [
            "遵守選舉法令，宏揚法治精神。 第一頁",
            "第一選舉區",
            "崙雅里、振興里、林厝里、出水里、湖水里、大",
            "里、鎮興里、浮圳里、西東里、南東里、",
            "中東里、東北里",
            "四名 應有婦女當選名額一名",
            "第二選舉區 東和里、民生里、黎明里、惠來里、中央里、溝皂里、大饒里、大明里、萬年里 四名 應有婦女當選名額一名",
            "第三選舉區",
            "中正里、仁美里、新興里、和平里、光明里、中山里、三條里、三和里、三橋里、三愛里、",
            "三信里、三多里、忠孝里、仁愛里",
            "七名 應有婦女當選名額一名",
            "第四選舉區 三義里、新生里、南平里、南興里、源潭里、大埔里 四名 應有婦女當選名額一名",
            "i",
            "幸福，選舉不買票、不賣票，要檢舉",
            "檢舉賄選專線：",
            "0800-024-099",
            "，撥通按",
            "4",
            "。"
        ]
    }
}