{
    "1": {
        "26 26 2740 237": [
            "臺灣省嘉義市議會第9屆議員選舉，經定於㆗華民國㆒百零㆔年㈩㆒㈪㆓㈩㈨㈰（星期㈥）㆖午㈧時起㉃㆘午㆕時止舉行投",
            "票。茲依公職㆟員選舉罷免法第㆕㈩㈦條規定，將候選㆟所填之政見及個㆟㈾料刊登如㆘，候選㆟個㆟㈾料係依據候選㆟所",
            "嘉義市選舉委員會 編印"
        ],
        "26 241 2740 399": [
            "填列㈾料刊登，如㈲不實，由候選㆟㉂行負責。",
            "姓㈴",
            "出生",
            "年㈪㈰",
            "性別 ㈻　　歷 經　　歷",
            "政　　見",
            "出生㆞",
            "推薦之",
            "政黨",
            "相 片"
        ],
        "26 402 130 507": [

        ],
        "131 402 388 507": [

        ],
        "390 402 512 507": [

        ],
        "514 402 673 507": [

        ],
        "675 402 797 507": [
            "",
            "62",
            "4"
        ],
        "799 402 964 507": [

        ],
        "966 402 1137 507": [

        ],
        "1139 402 1393 507": [
            "一、仁義中學高中畢業"
        ],
        "1395 402 1831 507": [
            "一、輔仁中學第43屆家長會常務委員",
            "二、嘉義市阿九後援會召集人"
        ],
        "1833 402 2740 507": [
            "一、督促市府加強提昇各處局的執行率要確實落實。",
            "二、督促市府加強照顧勞工、弱勢團體、婦幼、殘障等，提昇社會福利。",
            "三、協助市府，向中央爭取各基層建設的補助經費，建設發展嘉義市。",
            "四、協助市府，全力打造發展觀光事業，提昇商機，活絡市場。"
        ],
        "26 509 130 728": [

        ],
        "390 509 512 728": [

        ],
        "514 509 673 728": [

        ],
        "675 509 797 728": [
            "",
            "72",
            "3",
            "",
            "27"
        ],
        "799 509 964 728": [
            "臺灣省",
            "高雄市女"
        ],
        "966 509 1137 728": [

        ],
        "1139 509 1393 728": [
            "南華大學非營利事業管",
            "理研究所、國立嘉義大",
            "學生物事業管理系、輔",
            "二、民生國中畢業"
        ],
        "1395 509 1831 728": [
            "全發堂蔘藥總經理",
            "台日非政府組織論壇代表",
            "教育部教卓獎觀察員",
            "玉龍慈善會理事",
            "父母成長協會、嘉北校友會顧問",
            "三、馬蕭競選總部、副主任委員",
            "四、嘉義市第7、8屆市議員"
        ],
        "1833 509 2740 728": [
            "一、奕德發揮管理學識，秉持有學養善心正派問政，隨時聽候民眾吩咐，願為「民意急先鋒」，致力「守護嘉義、振興東區」使命。",
            "二、促進「教育」：(1)建請校舍全面安檢，保障師生安全。(2)建議發展各校特色，提供多元就學選擇。(3)督促本市圖書系統全面e化，便利親子共享",
            "教學資源。(4)督促保障國中小教師工作權，協助超額教師安置。",
            "三、促進「觀光」：(1)建請推動北門驛、後驛、檜意森活村資源整合，規劃「大北門商圈」促進繁榮。(2)建請補助東市場、南田市場攤商環境提升，",
            "成為雲嘉南集貨交易中心。(3)建請設立市容美化經費，經核准後個人、社區、里，可補助美化環境。(4)建議打造本市新地標，配合在地文化，推",
            "動遊客來嘉旅遊套裝行程。(5)督促重用在地文創人才，活化文創園區，增加觀光價值。",
            "四、促進「社福」：(1)建請低收入戶與獨居長者三餐、醫療費用全額補助。(2)建請放寬受難者急難救助金。(3)建請辦理失親幼兒免費托育及獨居長者",
            "五、督促市府，全面做好公共衛生，保障百姓的生命安全。",
            "六、督促市府社會福利優先，妥善照顧老人、兒童、婦女、勞工、攤販、身心障礙弱勢族群權益。",
            "七、嚴格為市民預算把關，妥善支配各項經費，當用則用，當省則省。",
            "八、全力督促市府做好八掌溪兩岸規劃，及行水區做好長遠完美計劃。"
        ],
        "340 671 388 727": [

        ],
        "131 680 179 728": [

        ],
        "26 730 130 950": [

        ],
        "131 730 179 950": [
            "2"
        ],
        "340 730 388 950": [

        ],
        "390 730 512 950": [

        ],
        "514 730 673 950": [

        ],
        "675 730 797 950": [
            "",
            "11",
            "",
            "61",
            "1"
        ],
        "799 730 964 950": [
            "嘉義市",
            "男",
            "臺灣省"
        ],
        "966 730 1137 950": [

        ],
        "1139 730 1393 950": [
            "仁高中、嘉華中學、民",
            "族國小",
            "美國加州亞格斯大學國貿博士",
            "美國加州AU財管暨會計碩士",
            "美國OKCU財管碩士",
            "東海大學會計系"
        ],
        "1395 730 1831 950": [
            "北門民防分隊長、義消鳳凰志工隊、南門義警顧問",
            "吳鳳獅子會、企業經理協進會員",
            "桃城獅子會、新鮮事協會顧問",
            "慈濟宮、聖興宮、先天宮顧問",
            "民視電視公司財務專員",
            "北門警友站顧問"
        ],
        "1833 730 2740 950": [
            "五、督促維護協勤民力(義警、民防、義消、義交、巡守隊等)安全，爭取裝備全面到位。",
            "六、督促全面檢視本市排水、積水問題，免除民眾水患之苦。",
            "七、建請成立婦女暨新住民技能學習中心，免費教導生活及職業技能。",
            "八、建請成立人力發展中心，提供公教、企經人員進修研習。",
            "九、建請成立青少年休閒中心，提供展演、活動場所。",
            "十、建請動物收容環境更進步，協助聯絡愛心飼主，確切解決流浪動物問題。",
            "一、反黑箱，反貪腐，要清廉",
            "二、重視街頭藝人表演權益",
            "三、爭取創意市集設立場所",
            "四、督促市府財政預算，為市民看緊荷包"
        ],
        "26 952 130 1171": [

        ],
        "390 952 512 1171": [

        ],
        "514 952 673 1171": [

        ],
        "675 952 797 1171": [
            "",
            "25",
            "",
            "78",
            "7"
        ],
        "799 952 964 1171": [
            "嘉義市",
            "男"
        ],
        "966 952 1137 1171": [

        ],
        "1139 952 1393 1171": [
            "協同中學高中部",
            "興華中學國中部",
            "師專附小",
            "國立虎尾高級中學"
        ],
        "1395 952 1831 1171": [
            "慶安鋼鐵股份有限公司總經理",
            "太陽花學運糾察",
            "青年佔領政治嘉義負責人"
        ],
        "1833 952 2740 1171": [
            "五、督促市政營造有利的條件，吸引企業廠商投資，提供更多就業機會",
            "六、推動商業與觀光新亮點，吸引觀光人潮，行銷嘉義",
            "七、支持爭取設立青年創業園區",
            "1.「繁榮嘉義市」推動嘉義成為公平貿易城市，改善經濟環境，提升嘉義競爭力。",
            "2.「生態嘉義市」推動《嘉義市樹木保護自治條例》，要求市府落實便利低碳交通，並設立空氣汙染警示告知系統，",
            "為嘉義市民爭取更好的生活環境。",
            "3.「文化嘉義市」推動嘉義市內文化資產保存，藉由市內文藝復興運動，增闢觀光產業市場，提供在地青年多元就業",
            "機會。"
        ],
        "26 1173 130 1392": [

        ],
        "390 1173 512 1392": [

        ],
        "514 1173 673 1392": [

        ],
        "675 1173 797 1392": [
            "",
            "17",
            "",
            "48",
            "3"
        ],
        "799 1173 964 1392": [
            "女",
            "臺北市",
            "臺灣省"
        ],
        "966 1173 1137 1392": [

        ],
        "1139 1173 1393 1392": [
            "國立中正大學政治研究所"
        ],
        "1395 1173 1831 1392": [
            "嘉義青年陣線召集人",
            "嘉義市第5、6、7、8屆議員",
            "嘉義市濟美仁愛之家董事長",
            "中華民國學生棒球運動聯盟會長"
        ],
        "1833 1173 2740 1392": [
            "4.「友善嘉義市」推動TNR零撲殺、居住正義、性\/別、無障礙空間等多元友善社會，結合府會合作，擘劃幸福遠景。",
            "5.「樂活嘉義市」推動社區醫療與長照事業、獎勵社區托育與共學，發展樂活農場、青年運動社團，並具體監督嘉義",
            "市安全食物與食育。",
            "6.「民主嘉義市」，支持修憲降低參政年齡門檻與保證金門檻，嚴守透明政治原則，使議會透明化運作；力行乾淨選",
            "舉，並於未來定期將議程交由公民審議，全民參與議會。",
            "一、監督市政，反映民意，爭取經費，落實地方建設。",
            "二、協助爭取社會救助和各項社會福利，重視老、弱、婦、幼照顧和教養等問題。",
            "三、改善公教人員升遷制度。",
            "四、解決教職人員休假問題。",
            "五、加速都更計劃，繁榮城市利基。"
        ],
        "131 1336 179 1392": [

        ],
        "340 1336 388 1392": [

        ],
        "26 1394 130 1613": [

        ],
        "390 1394 512 1613": [

        ],
        "514 1394 673 1613": [

        ],
        "675 1394 797 1613": [
            "",
            "52",
            "4",
            "",
            "18"
        ],
        "799 1394 964 1613": [
            "臺灣省",
            "嘉義縣",
            "男"
        ],
        "966 1394 1137 1613": [

        ],
        "1139 1394 1393 1613": [
            "立功幼稚園",
            "民族國小",
            "蘭潭國中",
            "碩士"
        ],
        "1395 1394 1831 1613": [
            "嘉義市社區規劃師",
            "東川里里長",
            "救國團東區委員會會長",
            "籃球推廣協會理事長",
            "後指部東區輔導中心主任",
            "警察局志工東區分隊長",
            "國民黨十九全中央委員",
            "私立大同技術學院講師"
        ],
        "1833 1394 2740 1613": [
            "一、推動觀光產業，讓嘉義市成為阿里山下的旅遊城市，結合現有觀光軸帶，推出觀光列車暢遊嘉義市，並打造嘉義成",
            "為一個充滿文創商品、特色小吃、文化藝術、休閒慢活的新興購物城市、帶來觀光人潮、創造商機與就業機會。",
            "二、繼續爭取嘉義創新研發中心第二期工程、提升產業界產品品質、增加競爭力。",
            "三、設置現代化工業區，爭取各界優良廠商前來設廠及大陸台商回國建廠，以增加就業人口和稅捐。",
            "四、廢除都市內零星工業區，讓都市計劃內已經停工的工業用地，能活化再運用。",
            "六、促進產業發展，擴大就業市場，引領企業進駐。",
            "七、整合觀光資源，提升文創價值。",
            "八、重視教育文化，培育在地人才。",
            "九、延續棒球王國之光，推動棒球運動。",
            "十、推動社區營造及社區守望相助，提升市民居住環境的品質及安全。"
        ],
        "131 1555 179 1613": [

        ],
        "341 1558 388 1613": [

        ],
        "26 1615 130 1834": [

        ],
        "390 1615 512 1834": [

        ],
        "514 1615 673 1834": [

        ],
        "675 1615 797 1834": [
            "",
            "29",
            "",
            "66",
            "10"
        ],
        "799 1615 964 1834": [
            "嘉義市",
            "男",
            "臺灣省"
        ],
        "966 1615 1137 1834": [

        ],
        "1139 1615 1393 1834": [
            "南榮科技大學(專科部)",
            "中正大學戰國所碩士",
            "國立中正大學社會科學院",
            "戰略暨國際事務研究所戰",
            "略暨國家安全碩士學位"
        ],
        "1395 1615 1831 1834": [
            "青溪協會理事長",
            "香功協會理事長",
            "興嘉劍道協會理事長",
            "槌球委員會主委",
            "家長協會顧問",
            "嘉義市東區長竹里里長",
            "嘉義市東區長竹社區發展協會理事長"
        ],
        "1833 1615 2740 1834": [
            "五、為下一代爭取更優質的教育環境",
            "　　1.落實教育向下紮根，提高幼兒教育補助金。",
            "　　2.提升國中小教育經費，改善教育環境，落實營養午餐食的品質，要求教育處重視四維八德與倫理教育。",
            "六、做市民的代言人，為市民爭權利謀福祉，當弱勢團體的發言人，用熱忱親切有效率的行動力，盡心盡力做好選民服",
            "務。",
            "提高公共休閒資源使用率，推動公園主題化。",
            "推動城市觀光資源建設，創造觀光新亮點。",
            "推動路平專案，改善市容與提升交通安全。",
            "整合學校發展主題競技運動，爭取專任教練名額、專業設備與經費。",
            "注重運動休閒環境之硬體設施維護與更新。",
            "改善棒球場軟硬體設備，爭取職棒在嘉義比賽場次。"
        ],
        "26 1836 130 2055": [

        ],
        "390 1836 512 2055": [

        ],
        "514 1836 673 2055": [

        ],
        "675 1836 797 2055": [
            "",
            "37",
            "7",
            "",
            "20"
        ],
        "799 1836 964 2055": [
            "臺灣省",
            "嘉義縣",
            "男"
        ],
        "966 1836 1137 2055": [

        ],
        "1139 1836 1393 2055": [
            "1.東吳大學理學院",
            "數學系畢業",
            "2.嘉義高中",
            "私立輔仁大學體育學系",
            "學士學位"
        ],
        "1395 1836 1831 2055": [
            "1.現任中央里里長",
            "2.市立大業國中教師",
            "3.市立北興國中教師",
            "4.縣立大林國中教師",
            "統一獅職棒隊投手",
            "嘉南勇士職棒隊投手"
        ],
        "1833 1836 2740 2055": [
            "1.建議在各大樓、集會所、廟宇的管理室裝設AED(自動體外心臟除顫器)。",
            "2.振興農工商生物科技產業，以促進就業機會。",
            "3.妥善支配各項預算落實地方各項建設。",
            "4.深耕教育推展書中自有黃金屋。",
            "推動身障運動文化。",
            "整合運動休閒資源，爭取綜合體育運動中心。",
            "提高弱勢學生就學補助。",
            "提高校園生活安全及食安抽檢率。",
            "落實中小學一校一特色發展。"
        ],
        "131 1904 212 1927": [

        ],
        "131 2027 179 2055": [

        ],
        "26 2057 130 2277": [

        ],
        "390 2057 512 2277": [

        ],
        "514 2057 673 2277": [

        ],
        "675 2057 797 2277": [
            "",
            "31",
            "7",
            "",
            "24"
        ],
        "799 2057 964 2277": [
            "臺灣省",
            "嘉義市",
            "男"
        ],
        "966 2057 1137 2277": [

        ],
        "1139 2057 1393 2277": [
            "政工幹部學校政治學系",
            "3.嘉義國中",
            "4.崇文國小"
        ],
        "1395 2057 1831 2277": [
            "考試院乙等人事行政特考及格",
            "國防大學政治學系",
            "文化大學政治學研究所",
            "民進黨嘉義市第三屆市長提名人　",
            "第一、二、四、五、六、七、八屆市議員",
            "無黨問政聯盟黨團總召",
            "5.縣立新港國中教師",
            "6.縣立大埔國中教師",
            "7.私立仁義高中教師兼學務主任",
            "8.國立彰化師大教育學院結業"
        ],
        "1833 2057 2740 2277": [
            "一、秉持清廉問政，專職為民服務，真實反映民意，堅守民代職責。",
            "二、全力配合市府向中央極力爭取建設經費，促使地方發展，繁榮、進步，建構幸福城市。",
            "三、督促市府社會福利優先，妥善照顧老人、兒童、婦女、勞工、攤販、身心障礙弱勢族群權益。",
            "四、督促市府從寬編列教育文化預算、改善師資、設備、環境及早落實小班教學，提升教學品質及加強文化",
            "　　資產的保存維護。",
            "5.督促政府崇尚法治建設和諧安寧的社會。",
            "6.力行環保綠能給下一代乾淨的家園。",
            "7.改善治安塑造安全健康的社會。",
            "8.監督市政改善財政赤字。"
        ],
        "26 2278 130 2498": [

        ],
        "390 2278 512 2498": [

        ],
        "514 2278 673 2498": [

        ],
        "675 2278 797 2498": [
            "",
            "32",
            "7",
            "",
            "5"
        ],
        "799 2278 964 2498": [
            "臺灣省",
            "男",
            "嘉義市"
        ],
        "966 2278 1137 2498": [

        ],
        "1139 2278 1393 2498": [
            "一、大同國小",
            "二、省立嘉義初商",
            "法學士"
        ],
        "1395 2278 1831 2498": [
            "一、嘉義市政府專員",
            "二、嘉義市議會第1、2、3、4、5、6、8屆市議員",
            "三、嘉南水利會第6、7、8屆會員代表",
            "嘉市仁愛慈善會、早泳會、公教退休協會名譽理事長",
            "嘉邑奉天宮名譽主委",
            "海軍陸戰隊連長",
            "林森國小、蘭潭國中、嘉義國中家長會長",
            "偉堅企業公司總經理",
            "嘉義旅行社董事長"
        ],
        "1833 2278 2740 2498": [
            "一、深入基層，了解民疾民苦。",
            "二、為民喉舌，確實反映民意。",
            "三、積極督促，市府依法行政。",
            "四、監督預算，看緊市民荷包。",
            "五、督促市府重視學生受教權及教師尊嚴與福利權益。",
            "六、督促市府盡速開闢全市八米計畫道路巷道，以利人車通行，俾以保障市民生命財產安全。",
            "七、督促市府加強治安維護，充實警用器材及配備，普設監視系統，以提高破案率，建構安全城市。",
            "八、督促市府加強與鄰近縣市觀光資源結合，提高觀光產業，建構對外交通網路，打造嘉義市為雲嘉南觀光",
            "　　休閒旅遊中心。"
        ],
        "131 2435 179 2498": [

        ],
        "340 2449 388 2498": [

        ],
        "26 2500 130 2719": [

        ],
        "131 2500 388 2642": [
            "10"
        ],
        "390 2500 512 2719": [

        ],
        "514 2500 673 2719": [

        ],
        "675 2500 797 2719": [
            "",
            "49",
            "10",
            "",
            "11"
        ],
        "799 2500 964 2719": [
            "臺灣省",
            "嘉義市",
            "男"
        ],
        "966 2500 1137 2719": [

        ],
        "1139 2500 1393 2719": [
            "嘉義市立北興國中",
            "三、吳鳳高中",
            "四、吳鳳工專"
        ],
        "1395 2500 1831 2719": [
            "嘉義市第四、五、七屆市議員",
            "四、嘉義縣議會第10屆縣議員",
            "五、嘉義市代表會第9屆市民代表",
            "六、嘉義市農會第2屆理事"
        ],
        "1833 2500 2740 2719": [
            "一、監督市政為市民爭取福利。",
            "二、爭取經費建設大嘉北地區。",
            "五、敦促市府，加強便民措施。",
            "六、負責盡職，扮好民代角色。",
            "七、施政計劃，以民意為依歸。",
            "八、市政建設，以全民為鵠的。"
        ],
        "341 2671 388 2706": [

        ],
        "131 2672 179 2719": [

        ],
        "26 2721 130 2940": [

        ],
        "390 2721 512 2940": [

        ],
        "514 2721 673 2940": [

        ],
        "675 2721 797 2940": [
            "",
            "17",
            "",
            "56",
            "1"
        ],
        "799 2721 964 2940": [
            "嘉義市",
            "男",
            "臺灣省"
        ],
        "966 2721 1137 2940": [

        ],
        "1139 2721 1393 2940": [
            "高雄市私立復華高中",
            "國立中正大學EMBA高階",
            "主管管理研究所碩士"
        ],
        "1395 2721 1831 2940": [
            "一、嘉義市第七、八屆議員",
            "二、民進黨嘉義市黨部第十四屆主任委員",
            "三、嘉義市民連署運動發起人",
            "四、黃玫瑰運動發起人"
        ],
        "1833 2721 2740 2940": [
            "三、照顧弱勢團體為老年長者爭取福利。",
            "四、爭取大企業到嘉義設廠，增加工作機會，讓更多年輕人回鄉服務。",
            "一、全力推動嘉義市〝全環保自然小學〞2座(推動教育革新運動)。",
            "二、推動〝流浪貓狗動物零撲殺計畫〞(日本熊本市的成功模式)。",
            "三、推動在地〝食物銀行計畫〞讓需要幫助的人獲得及時的援助。",
            "四、推動黃玫瑰運動。(卸任總統、副總統須被限制出境2年，接受調查)。",
            "五、推動「市民聯署運動」。A1全力推動「嘉義市國中、小學營養午餐免費」",
            "　　　　　　　　　　　　　A2爭取興建「東、西區各一座市民運動中心」。"
        ],
        "131 2855 179 2940": [

        ],
        "340 2885 388 2940": [

        ],
        "26 2942 130 3161": [

        ],
        "131 2942 388 3161": [
            "12"
        ],
        "390 2942 512 3161": [

        ],
        "514 2942 673 3161": [

        ],
        "675 2942 797 3161": [
            "",
            "43",
            "5",
            "",
            "13"
        ],
        "799 2942 964 3161": [
            "臺灣省",
            "女",
            "嘉義市"
        ],
        "966 2942 1137 3161": [

        ],
        "1139 2942 1393 3161": [
            "台灣大學三民主義研究所",
            "碩士",
            "台灣大學法律系",
            "中華醫事技術學院醫檢",
            "科畢業"
        ],
        "1395 2942 1831 3161": [
            "國立嘉義高中公民教師",
            "教師人權促進會嘉義分會創會會長",
            "中華民國荒野保護協會嘉義分會創會會長",
            "嘉義地方法院調解委員",
            "五、嘉義市立兒童館館長",
            "六、民進黨嘉義市黨部婦女組組長",
            "七、民進黨第11～13屆全國黨代表",
            "八、民進黨中央執行委員、民進黨中央評議委員"
        ],
        "1833 2942 2740 3161": [
            "一、反併吞，維護台灣主權；",
            "二、監督市政府：(一)推動結合人文歷史，發展城市觀光；",
            "　　　　　　　　(二)營造健康優活全民安居的城市；",
            "六、督促市府開闢道路時應設置公共管道，提高管理效率與防災，維護道路，市容觀瞻。",
            "七、督促市府全面規設無障礙設施空間，保障身障者生活權益。",
            "八、督促衛生單位落實各項預期功能，以確保市民醫療、照護品質。",
            "九、爭取提高警消人員加勤費及獎勵金，充實器材設備。",
            "十、爭取設置社區老人照護中心，比照其他縣市65歲至69歲健保費全額補助。"
        ],
        "26 3163 130 3382": [

        ],
        "390 3163 512 3382": [

        ],
        "514 3163 673 3382": [

        ],
        "675 3163 797 3382": [
            "",
            "47",
            "8",
            "",
            "5"
        ],
        "799 3163 964 3382": [
            "臺灣省",
            "嘉義縣",
            "女"
        ],
        "966 3163 1137 3382": [

        ],
        "1139 3163 1393 3382": [
            "一、輔仁中學畢業",
            "國立嘉義女中",
            "崇文國小"
        ],
        "1395 3163 1831 3382": [
            "1.中醫師檢定考試及格",
            "2.市議會警政小組召集人",
            "3.體育會首席顧問",
            "4.清水寺首席顧問",
            "5.石雕協會首席顧問",
            "6.愛家協會顧問",
            "現任：桃山人文館館長、快樂公民學苑創辦人",
            "　　　嘉義基督教醫院志工",
            "　　　教育部第4屆本土教育會委員"
        ],
        "1833 3163 2740 3382": [
            "1.督促市府全面檢討改善淹水問題。",
            "2.要求市府逐年編列經費徵收開闢8米計畫道路。",
            "3.督促市府積極進行管線地下化。",
            "4.繼續督促市府早日完成湖仔內區段徵收，並幫市民解決徵收過程中的大小問題。",
            "5.全力督促市府做好八掌溪兩岸規劃，及行水區做好長遠完美計畫。",
            "　　　　　　　　(三)落實本土教育，多元適性的教育，俾愛鄉土及人盡其才，各盡其能。",
            "　　　　　　　　(四)振興經濟，發展在地特色產業，落實雲嘉休閒消費的中心。",
            "　　　　　　　　(五)推動公共參與，打造公民社會。"
        ],
        "341 3324 388 3382": [

        ],
        "131 3334 179 3382": [

        ],
        "26 3384 130 3604": [

        ],
        "131 3384 388 3480": [
            "14"
        ],
        "390 3384 512 3604": [

        ],
        "514 3384 673 3604": [

        ],
        "675 3384 797 3604": [
            "",
            "71",
            "2",
            "",
            "10"
        ],
        "799 3384 964 3604": [
            "臺灣省",
            "雲林縣",
            "男"
        ],
        "966 3384 1137 3604": [

        ],
        "1139 3384 1393 3604": [
            "1.嘉師附小",
            "崇文國小(舞蹈班)",
            "2.蘭潭國中(美術班)",
            "大業國中",
            "二、國立嘉義高中畢業"
        ],
        "1395 3384 1831 3604": [
            "現任：嘉義市第八屆議員",
            "7.義交大隊顧問",
            "8.觀光商務協會顧問",
            "9.興安國小、大業國中家長會顧問",
            "10.一貫道道親（慈善堂、發一崇德）",
            "11.淡水工專（真理大學前身）肄業"
        ],
        "1833 3384 2740 3604": [
            "嘉義市是個小城，除了經濟發展，嘉義人對於自己家鄉的居住共感也應該被提昇，戴寧以現任議員的經驗，以及對一",
            "個宜居家園的想像出發",
            "戴寧想推動：",
            "1.友善的自行車行車環境，及提案規劃自行車專屬交通網路",
            "2.市內公車免費及更有效、完善的行車路線",
            "3.嚴重空污PM2.5相關因應政策的催生督促",
            "6.爭取義交、義消、民防、義警相關福利預算。",
            "7.協助觀光商務協會爭取應有的福利。",
            "8.協助石雕協會爭取更多的中央及地方政府補助。",
            "9.全心全力服務市民(市民的跑步鞋)。",
            "全心全力監督市政(市政的抓漏師)。"
        ],
        "131 3525 179 3604": [

        ],
        "340 3528 388 3604": [

        ],
        "26 3605 130 3825": [

        ],
        "131 3605 388 3778": [
            "15"
        ],
        "390 3605 512 3825": [

        ],
        "514 3605 673 3825": [

        ],
        "675 3605 797 3825": [
            "",
            "41",
            "1",
            "",
            "23"
        ],
        "799 3605 964 3825": [
            "臺灣省",
            "嘉義市",
            "女"
        ],
        "966 3605 1137 3825": [

        ],
        "1139 3605 1393 3825": [
            "淡江大學英國語文學系",
            "輔仁高中",
            "3.國立嘉義高商",
            "4.台中技術學院(二年制)",
            "5.嘉南藥理科技大學"
        ],
        "1395 3605 1831 3825": [
            "輔仁高中英文老師",
            "嘉義市第七、八屆議員"
        ],
        "1833 3605 2740 3825": [
            "落實台聯黨的宗旨與價值：",
            "(A)顧嘉義市：",
            "(1)清廉參政，絕不買票賄選。",
            "(2)嚴格監督市政與公共工程，杜絕弊端，確保市政與公共工程品質。",
            "(3)嚴謹審查預算，杜絕浪費。",
            "4.協助爭取在地青壯年所需的創業資源，活絡城市的多樣性及庶民文化",
            "5.屬於全體市民的藝文電影院",
            "6.全面檢討嘉義市現有公園、廣場及都市計劃中未來之公園用地之實用性與需要性，進一步對功能不明確之公共空間",
            "進行改造提案",
            "請支持戴寧，讓我們攜手為家鄉最美好的樣子努力！"
        ],
        "26 3827 130 4043": [

        ],
        "390 3827 512 4043": [

        ],
        "514 3827 673 4043": [

        ],
        "675 3827 797 4043": [
            "",
            "21"
        ],
        "799 3827 964 4043": [
            "嘉義市",
            "男"
        ],
        "966 3827 1137 4043": [
            "◎選舉投票有關規定、投（開）票所一覽表：詳見第9屆市長選舉選舉公報。"
        ],
        "1139 3827 1393 4043": [
            "輔仁初中",
            "大同國小"
        ],
        "1395 3827 1831 4043": [
            "若竹文教基金董事",
            "家扶永久認養人"
        ],
        "1833 3827 2740 4042": [
            "(4)市民看得到，央得到，服務免伴手。",
            "(B)護台灣：",
            "(1)主張暫緩實施令全民跳腳痛苦的急就章之「12國教免試免費升學」政策。",
            "(2)主張國教向下延伸，五歲入學，減輕家長負",
            "担",
            "，減少少子化壓力及充分學校硬體設備。",
            "(3)主張高職先行免試、免學雜費。"
        ]
    }
}