{
    "1": {
        "12 495 2916 708": [
            "選人自行負責。"
        ],
        "12 714 79 893": [

        ],
        "81 714 147 893": [

        ],
        "149 714 346 893": [

        ],
        "347 714 487 893": [

        ],
        "489 714 544 893": [

        ],
        "546 714 601 893": [

        ],
        "602 714 640 893": [

        ],
        "642 714 680 893": [

        ],
        "682 714 825 893": [
            "70"
        ],
        "827 714 970 893": [

        ],
        "972 714 1461 893": [
            "台灣在地文化交",
            "一、保護樹木、增加綠地",
            "1.護樹優於種樹，植樹節改為護樹節。",
            "2.落實都市計畫法規定，綠地面積應達到十分之一。",
            "二、愛護動物、尊重生命",
            "1.地方政府面對TNR（捕捉、結紮、回放）政策，精準捕捉攻擊性流浪",
            "動物，消除不當撲殺。",
            "2.保護野生動物棲息地，維護地方生物多樣性資產。",
            "3.推廣地方生命教育、輔導解決與動物衝突的處理、建立與動物共生",
            "共存的友善鄉里。"
        ],
        "1467 714 1537 893": [

        ],
        "1539 714 1605 893": [

        ],
        "1607 714 1803 893": [
            "積 穗 里"
        ],
        "1805 714 1945 893": [

        ],
        "1947 714 2002 893": [

        ],
        "2004 714 2059 893": [

        ],
        "2060 714 2098 893": [

        ],
        "2100 714 2138 893": [

        ],
        "2140 714 2283 893": [
            "45"
        ],
        "2285 714 2428 893": [
            "臺灣省南投縣",
            "中國國民黨"
        ],
        "2430 714 2916 893": [
            "一、強化里民居住安全，平時建立安全意識",
            "1.持續深化每年防火、防災宣導課程。",
            "2.強化巡守隊每日安全巡護，提昇環境安全及防災專業知識。",
            "3.不定期開設居家安全講座，建立鄰居相互守望防護。",
            "4.加強警察、消防單位聯繫，做到隨叫隨到。",
            "二、打造節能減碳、綠化美化的宜居環境",
            "1.定期邀請專家講授，節能減碳及美化課程，倡導低碳生活方式。",
            "2.繼續爭取綠化美化經費，強化本里生活環境。",
            "3.持續環保義工每月二次的里內環境大掃除。"
        ],
        "12 895 79 1318": [

        ],
        "81 895 147 1318": [

        ],
        "149 895 346 1318": [
            "景 安 里",
            "1"
        ],
        "347 895 487 1318": [

        ],
        "489 895 544 1318": [

        ],
        "546 895 601 1318": [
            "黃 雅 婕"
        ],
        "602 895 640 1318": [

        ],
        "642 895 680 1318": [

        ],
        "682 895 825 1318": [
            "11",
            "6",
            "女",
            "45"
        ],
        "827 895 970 1318": [
            "臺北市",
            "樹黨",
            "中和國民小學",
            "中和國民中學",
            "德霖技術學院專",
            "科部",
            "中國國民黨"
        ],
        "972 895 1461 1318": [
            "流協會助理",
            "台灣貓狗人協會",
            "現任理事",
            "北部公立收容所",
            "志工隊現任隊長",
            "4.實質支持鼓勵認養代替購買。加強飼主責任感，落實寵物植晶片。",
            "鼓勵檢舉棄養的行為。",
            "三、低碳城市、在地經濟",
            "1.落實環境基本法，非核家園條款，實踐能源節約與自主，執行氣候",
            "變遷的減量與調適計畫。",
            "2.發展經濟自主的在地幸福經濟、振興地方商圈及傳統市場、鼓勵公",
            "平貿易、反對服貿及自由經濟示範區。",
            "3.勞動與青年就業，公部門禁止使用派遣人力，推動有尊嚴的綠領工",
            "作機會。",
            "四、陽光政治、地方平權",
            "1.從地方基層推動參與式民主。",
            "2.重大政策及爭議案件應先辦理行政聽證，確認開發必要性與可行",
            "性，再進行環評，都市計畫變更，文化資產及樹木保護等審議程",
            "序。",
            "3.支持青年權益及參政權。",
            "1.建設看得到，隨時隨地找得到。",
            "景安里里長",
            "林姓宗親會理",
            "事",
            "長生會常務理",
            "事",
            "1",
            "2",
            "3"
        ],
        "1467 895 1537 1318": [

        ],
        "1539 895 1605 1318": [

        ],
        "1607 895 1803 1318": [
            "1"
        ],
        "1805 895 1945 1318": [

        ],
        "1947 895 2002 1318": [

        ],
        "2004 895 2059 1318": [
            "石 淑 鳳"
        ],
        "2060 895 2098 1318": [

        ],
        "2100 895 2138 1318": [

        ],
        "2140 895 2283 1318": [
            "9",
            "18",
            "女",
            "48"
        ],
        "2285 895 2428 1318": [
            "老松國小",
            "華江女子國民中",
            "學",
            "臺灣省苗栗縣"
        ],
        "2430 895 2916 1318": [
            "新北市中和區積",
            "穗里  里長",
            "新北市中和區關",
            "懷社區福利協會",
            "理事長",
            "三、推動藝術人文氣息的生活圈",
            "1.定期邀請學者專家講授人文藝術課程。",
            "2.持續本里歌唱班、電腦班。",
            "3.開設國畫、書法班。",
            "4.持續定期舉辦民俗技藝活動。",
            "四、構建健康活力的社區",
            "1.持續本里的乒乓球隊及教學。",
            "2.持續本里國際標準舞及社交舞班隊及教學。",
            "3.持續本里戶外親子活動。",
            "4.定期邀請衛生所及雙和醫院醫師，舉辦健康講座。",
            "五、深化鄰居感情建立合諧正向的積穗里",
            "1.持續每年進香及出遊之里民聯誼活動。",
            "2.持續辦理普渡及各種宗教活動。",
            "3.擴大辦理每年元宵節、母親節、中秋節等，民俗節日之里民聯誼活動。",
            "4.持續愛心志工，定期關懷本里的獨居老人。",
            "牙技師法考選部",
            "及格",
            "新北牙技師公會",
            "理事"
        ],
        "12 1319 79 1742": [

        ],
        "81 1319 147 1742": [

        ],
        "149 1319 346 1742": [
            "2"
        ],
        "347 1319 487 1742": [

        ],
        "489 1319 544 1742": [

        ],
        "546 1319 601 1742": [
            "林 聰 憲"
        ],
        "602 1319 640 1742": [

        ],
        "642 1319 680 1742": [

        ],
        "682 1319 825 1742": [
            "49",
            "1",
            "15",
            "男"
        ],
        "827 1319 970 1742": [
            "中和國小畢",
            "中和國中畢",
            "智光商工畢"
        ],
        "972 1319 1461 1742": [
            "一、銓盈建設公司",
            "工地主任。",
            "二、中和第一分局",
            "安平義警分隊",
            "分隊長。中和",
            "一、配合社區發展舉辦各項活動、成立社團班隊。",
            "2.全面疏濬本里排水系統，徹底解決水患。",
            "3.徹底執行垃圾不落地，維護環境衛生。",
            "4.竭誠為里民服務、爭取里民福祉。",
            "5.促進里民團結和諧，創造美好的景安里。",
            "6.加強里內巡守，維護里內安全。",
            "7.路平，燈亮，水溝通。",
            "雲林同鄉會理",
            "事",
            "中和市黨部景",
            "安里常委",
            "久興五金行負",
            "責人",
            "100年 度 新 北",
            "市中和區特優",
            "里長",
            "4",
            "5",
            "6",
            "7"
        ],
        "1467 1319 1537 1742": [

        ],
        "1539 1319 1605 1742": [

        ],
        "1607 1319 1803 1742": [
            "民 享 里",
            "1"
        ],
        "1805 1319 1945 1742": [

        ],
        "1947 1319 2002 1742": [

        ],
        "2004 1319 2059 1742": [
            "何 炳 蓬"
        ],
        "2060 1319 2098 1742": [

        ],
        "2100 1319 2138 1742": [

        ],
        "2140 1319 2283 1742": [
            "47",
            "6",
            "17",
            "男"
        ],
        "2285 1319 2428 1742": [
            "無",
            "樹人醫護管理專",
            "科學校"
        ],
        "2430 1319 2916 1742": [
            "民享里里長",
            "一、配合區公所政令宣導。",
            "二、配合衛生所作里民健康檢查。",
            "新北市鑲牙齒模",
            "工會常務理事",
            "全聯會理事",
            "領導士官班長陸",
            "一特",
            "15鄰 長 巡 守 隊",
            "員",
            "在職專班長",
            "重視弱勢族群，老人照護"
        ],
        "12 1744 79 2166": [

        ],
        "81 1744 147 2166": [

        ],
        "149 1744 346 2166": [
            "3",
            "景 文 里"
        ],
        "347 1744 487 2166": [

        ],
        "489 1744 544 2166": [

        ],
        "546 1744 601 2166": [
            "游 任 是"
        ],
        "602 1744 640 2166": [

        ],
        "642 1744 680 2166": [

        ],
        "682 1744 825 2166": [
            "45",
            "3",
            "14",
            "男"
        ],
        "827 1744 970 2166": [
            "中國國民黨",
            "無",
            "東南技術學院機",
            "械工程學士畢"
        ],
        "972 1744 1461 2166": [
            "1.雙 和 青 商 會",
            "OB主席。",
            "2.中和區體育會",
            "監事。",
            "1.協助政府推行政令切實反應民意。",
            "國 小 93.94.96.",
            "97學年度家長",
            "會會長。新北",
            "市中和區六景",
            "社區發展協會",
            "理事。新北市",
            "警察之友會中",
            "和第一辦事處",
            "景安站顧問。",
            "二、協助里民辦理都市更新改善居住環境。",
            "三、配合派出所、義警、民防、巡守隊加強維護治安。",
            "四、爭取電線電纜地下化，以整市容，提昇居住品質。",
            "五、不分黨派為全里民服務。",
            "六、配合六景社區發展協會，舉辦老人共餐活動。",
            "七、設立服務中心，加強服務品質，以達更親民便。"
        ],
        "1467 1744 1537 2166": [

        ],
        "1539 1744 1605 2166": [

        ],
        "1607 1744 1803 2166": [
            "2",
            "員 山 里"
        ],
        "1805 1744 1945 2166": [

        ],
        "1947 1744 2002 2166": [

        ],
        "2004 1744 2059 2166": [
            "簡 民 利"
        ],
        "2060 1744 2098 2166": [

        ],
        "2100 1744 2138 2166": [

        ],
        "2140 1744 2283 2166": [
            "42",
            "9",
            "25",
            "男"
        ],
        "2285 1744 2428 2166": [
            "臺灣省屏東縣",
            "新北市",
            "無",
            "瑞芳國民中學"
        ],
        "2430 1744 2916 2166": [
            "臺北縣中和市第",
            "八屆里長",
            "新北市第一屆里",
            "長",
            "一、專業里長，專業團隊服務。",
            "二、協助里內中低收入戶辦理各項補助服務。",
            "三、積極維護里內路平，燈亮，水溝清，定期環境打掃。",
            "四、響應政府終生學習，加強辦理才藝班研習及各項公益活",
            "莒東社區理事",
            "自強國中、國小",
            "顧問常務委員",
            "民享里巡守隊隊",
            "長環保義工志工",
            "隊長",
            "三、配合消防隊作居家宣導。",
            "四、積極設立里內監視系統重建。",
            "五、全力辦理里民聯誼活動讓里民能團結和諧。",
            "六、全心全力服務里民。",
            "七、全力完成（民享選民利大家有福利目標）。",
            "八、路燈一定亮，路面一定平，水溝一定清。"
        ],
        "12 2168 79 2591": [

        ],
        "81 2168 147 2591": [

        ],
        "149 2168 346 2591": [
            "1",
            "錦 和 里"
        ],
        "347 2168 487 2591": [

        ],
        "489 2168 544 2591": [

        ],
        "546 2168 601 2591": [
            "林 東 銘"
        ],
        "602 2168 640 2591": [

        ],
        "642 2168 680 2591": [

        ],
        "682 2168 825 2591": [
            "7",
            "27",
            "男",
            "50"
        ],
        "827 2168 970 2591": [
            "新北市",
            "高中肄業"
        ],
        "972 2168 1461 2591": [
            "3.中和區體育會",
            "手球委員會主",
            "委。",
            "4.擔 任 中 和 市",
            "六、七、八屆",
            "景文里里長。",
            "5.擔任中和區第",
            "一屆景文里里",
            "長。",
            "2.重視鄰里需求加強基層建設。",
            "3.提升巡守功能加強治安系統連線。",
            "4.加強里內獨居老人、低收入戶、中低收入戶、身障者及單",
            "親家庭關懷服務並協助申辦各項津貼。",
            "5.落實熱誠服務精神。",
            "1.榮獲103年全國績優里長。",
            "2.榮獲103年新北市績優里長。",
            "3.成立環保資源回收站，回饋金辦理里內中低收入戶及國小國中",
            "獎勵金。",
            "4.每季不定期疏通水溝及全里環境消毒。",
            "5.全年無假日開設里民活動中心供鄉親使用。",
            "6.里活動中心設置桌球、健身器材、卡拉OK及數百本圖書提供"
        ],
        "1467 2168 1537 2591": [

        ],
        "1539 2168 1605 2591": [

        ],
        "1607 2168 1803 2591": [
            "1",
            "嘉 穗 里"
        ],
        "1805 2168 1945 2591": [

        ],
        "1947 2168 2002 2591": [

        ],
        "2004 2168 2059 2591": [
            "藍 國 鐘"
        ],
        "2060 2168 2098 2591": [

        ],
        "2100 2168 2138 2591": [

        ],
        "2140 2168 2283 2591": [
            "6",
            "23",
            "男",
            "52"
        ],
        "2285 2168 2428 2591": [
            "無",
            "屏東縣佳冬鄉玉",
            "光國小",
            "屏東縣省立潮中",
            "中學"
        ],
        "2430 2168 2916 2591": [
            "中和區青年廣場",
            "四任主任委員",
            "新北市海山國小",
            "家長會副會長",
            "新北市中和區慈",
            "心關懷協會理事",
            "長",
            "小秀才學堂員山",
            "里負責人",
            "動。",
            "五、積極爭取增設數位監視系統，提高里內生命財產之安",
            "全。",
            "六、積極協助里內污水下水道接管工程，提升生活品質。",
            "七、積極關心環狀捷運線，提升交通便利性及週邊環境規",
            "劃。",
            "八、消除髒亂點，定期消毒，協助大型廢棄物清運，維護里",
            "內環境衛生，提高生活品質。",
            "一、臺北縣中和市",
            "嘉穗里第六、",
            "七、八屆里長",
            "二、新北市中和區",
            "嘉穗里第一屆",
            "里長",
            "三、新北市中和區",
            "親子關懷協會",
            "一、秉持熱忱勤快、認真打拚、正直肯做的精神，繼續為里",
            "民服務。",
            "二、落實里民基本要求：1、路面平順；2、水溝暢通；3、",
            "路燈光亮如有損壞、立即修復。",
            "三、持續推動守望相助巡守隊，加強夜間巡邏工作，維護里"
        ],
        "12 2592 79 3015": [

        ],
        "81 2592 147 3015": [

        ],
        "149 2592 346 3015": [
            "1",
            "錦 昌 里"
        ],
        "347 2592 487 3015": [

        ],
        "489 2592 544 3015": [

        ],
        "546 2592 601 3015": [
            "林 進 明"
        ],
        "602 2592 640 3015": [

        ],
        "642 2592 680 3015": [

        ],
        "682 2592 825 3015": [
            "11",
            "20",
            "男",
            "54"
        ],
        "827 2592 970 3015": [
            "新北市",
            "無",
            "高中畢業",
            "中國國民黨"
        ],
        "972 2592 1461 3015": [
            "現任里長",
            "鄉親建身育樂場所，提昇書香文化氣息。",
            "7.開辦成長課程：瑜珈班、歌唱班、肚皮舞班。",
            "8.持續每年農曆過年（年初三）親自為鄉親清運垃圾乙次免鄉親",
            "家中放置垃圾造成異味，影響居家品質，12年來從不間斷。",
            "9.全面換新、補足滅火器，於每棟樓梯大門及樓梯內都設滅火",
            "器，加強消防設備。",
            "10.每年颱風期之前備請怪手清除369巷沉沙池雜物、淤泥，以",
            "利排水順暢。",
            "11.感謝盡職巡守隊員，守護鄉親居家安全及大愛無私環保志",
            "工，每個月2次的里內環境打掃及做資源回收，都是今日錦",
            "和里光榮。",
            "12.做里長不怕做事情，怕做事就不做里長，這是阿明的原則。",
            "臺北縣中和市第",
            "六、七、八屆錦",
            "昌里長。新北市",
            "中和區第一屆錦",
            "昌里長。益輝事",
            "業有限公司。錦",
            "用心用情用行動愛鄉里     誠懇勤快以熱忱來服務"
        ],
        "1467 2592 1537 3015": [

        ],
        "1539 2592 1605 3015": [

        ],
        "1607 2592 1803 3015": [
            "1"
        ],
        "1805 2592 1945 3015": [

        ],
        "1947 2592 2002 3015": [

        ],
        "2004 2592 2059 3015": [
            "陳 榮 鐘"
        ],
        "2060 2592 2098 3015": [

        ],
        "2100 2592 2138 3015": [

        ],
        "2140 2592 2283 3015": [
            "9",
            "18",
            "男",
            "36"
        ],
        "2285 2592 2428 3015": [
            "新北市",
            "無",
            "一、積穗國小",
            "二、積穗國中",
            "三、光華商職",
            "福建省金門縣"
        ],
        "2430 2592 2916 3015": [
            "常務理事",
            "四、新北市警察之",
            "友會中和辦事",
            "處員山站組長",
            "五、新北市中和區",
            "民安社區發展",
            "協會顧問",
            "六、新北市金圓山",
            "生命禮儀社負",
            "責人",
            "七、新北市中和區",
            "東德宮管理委",
            "員會主任委員",
            "內治安，讓里民安心生活無疑慮。",
            "四、持續推動環保清潔工作，定期打掃清理巷弄街道、防火",
            "巷，整治排水溝，環境消毒等工作，維護里民居家生活",
            "品質。",
            "五、定期更新消防滅火器設備，保護住戶身家安全。",
            "六、協助代辦中、低收入戶、老人居家生活津貼、各項急難",
            "救助等社會救助事項。",
            "七、舉辦各項才藝課程及親子相關活動，增加里民學習機",
            "會，提升里民素質，促進里民感情。",
            "1.積穗國中家長",
            "會會長。",
            "1.每座公共樓梯滅火器增加至每座樓梯四支滅火器。"
        ],
        "12 3017 79 3439": [

        ],
        "81 3017 147 3439": [

        ],
        "149 3017 346 3439": [
            "1",
            "灰      里"
        ],
        "347 3017 487 3439": [

        ],
        "489 3017 544 3439": [

        ],
        "546 3017 601 3439": [
            "范 文 輝"
        ],
        "602 3017 640 3439": [

        ],
        "642 3017 680 3439": [

        ],
        "682 3017 825 3439": [
            "11",
            "22",
            "男",
            "56"
        ],
        "827 3017 970 3439": [
            "新北市",
            "中和國小",
            "積穗國中",
            "開南商工"
        ],
        "972 3017 1461 3439": [
            "和國小家長委員",
            "會。中和國中家",
            "長委員會。中和",
            "高 中 家 長 委 員",
            "會。錦和高中家",
            "長委員會。永和",
            "國際青年商會。",
            "中華民國紳士協",
            "會。新北市范姓",
            "宗親會。革命實",
            "踐研究院",
            "1.關懷弱勢里民主動協助申請各項社會福利補助。",
            "2.開辦各項成長課程及健康講座，推展終身學習。",
            "3.加強守望相助及警網連繫共同打擊犯罪確實守護里民生命",
            "財產安全。",
            "4.建立e化通訊，儘速發佈政令訊息即時雙相聯繫交流，落實",
            "環境衛生清潔維護，營造更優質的居住環境。"
        ],
        "1467 3017 1537 3439": [

        ],
        "1539 3017 1605 3439": [

        ],
        "1607 3017 1803 3439": [
            "文 元 里",
            "1"
        ],
        "1805 3017 1945 3439": [

        ],
        "1947 3017 2002 3439": [

        ],
        "2004 3017 2059 3439": [
            "蔡 清 山"
        ],
        "2060 3017 2098 3439": [

        ],
        "2100 3017 2138 3439": [

        ],
        "2140 3017 2283 3439": [
            "5",
            "22",
            "男",
            "65"
        ],
        "2285 3017 2428 3439": [
            "無",
            "高中畢業"
        ],
        "2430 3017 2916 3439": [
            "2.中華民國金門",
            "烈嶼公共事務",
            "協會秘書長。",
            "3.臺北縣中和市",
            "第七屆文元里",
            "里長。",
            "2.每座公共樓梯口規劃禁止機車暫停黃線格。",
            "3.服務處開放時間從星期一至星期六早上九點至晚間九點",
            "（星期日例外）。",
            "4.每年至少一次旅遊活動，無論國內國外或自費或補助。",
            "5.當選後六個月至一年內即召開文元里里民大會。",
            "中和區員山派出",
            "所志工",
            "推動社區守望系統：召開社區治安會議保障婦女兒童安全",
            "推動社區照顧網絡：讓里內老人家、身心障礙者都能感受到"
        ],
        "12 3441 79 3864": [

        ],
        "81 3441 147 3864": [

        ],
        "149 3441 346 3864": [
            "1"
        ],
        "347 3441 487 3864": [

        ],
        "489 3441 544 3864": [

        ],
        "546 3441 601 3864": [
            "林 鑫 宏"
        ],
        "602 3441 640 3864": [

        ],
        "642 3441 680 3864": [

        ],
        "682 3441 825 3864": [
            "7",
            "3",
            "男"
        ],
        "827 3441 970 3864": [
            "新北市",
            "無",
            "積穗國中畢"
        ],
        "972 3441 1461 3864": [
            "鑫豪電子負責人",
            "中和市第7、8屆",
            "里長",
            "中和區第一屆現",
            "任里長",
            "將里內之空地、整治規劃為綠地公園，解決41-49號之排水",
            "工程，設置籃球場供民眾運動利用，請分局單位增設監視器",
            "維護治安，打擊犯罪，增設公園運動器材供里民使用，購置",
            "新運動器材於活動中心供民眾使用，定期做好排洪之工程整",
            "治。"
        ],
        "1467 3441 1537 3864": [

        ],
        "1539 3441 1605 3864": [

        ],
        "1607 3441 1803 3864": [
            "2"
        ],
        "1805 3441 1945 3864": [

        ],
        "1947 3441 2002 3864": [

        ],
        "2004 3441 2059 3864": [
            "吳 欣 怡"
        ],
        "2060 3441 2098 3864": [

        ],
        "2100 3441 2138 3864": [

        ],
        "2140 3441 2283 3864": [
            "9",
            "29",
            "女"
        ],
        "2285 3441 2428 3864": [
            "新北市",
            "無",
            "高職"
        ],
        "2430 3441 2916 3864": [
            "警察之友會員山",
            "站組長",
            "新北市美滿家庭",
            "推廣協會顧問",
            "新北市中和區文",
            "元里里長",
            "來自鄰里的關懷。",
            "推展社區教育：結合學校社會團體資源，開辦親子成長課程",
            "與各種講座，使里民更關心環保、生態、兩性平等議題",
            "爭取規劃閒置空地綠美化：讓里民有安全舒適美觀的休憩場",
            "所，化解社區的疏離與冷漠。",
            "成立資源回收站，將資收基金照顧里內低收入戶、獨居老人",
            "及急難救助金。"
        ],
        "12 3865 2916 4283": [

        ]
    }
}