{
    "1": {
        "180 265 3037 540": [
            "新北市新莊區（　　　　　　　　　　   ）第 2 屆里長選舉選舉公報",
            "新北市選舉委員會　編印",
            "立泰里、中原里、中平里、立德里",
            "立言里、中宏里、立志里、立功里",
            "立基里、立廷里"
        ],
        "180 545 3037 767": [
            "新北市新莊區第2屆里長選舉，經定於民國103 年11 月29日(星期六)上午8 時起至下午4 時止舉行投票。",
            "茲依公職人員選舉罷免法第 47 條規定，將候選人所填報之政見及個人資料刊登如下，候選人個人資料係依據",
            "候選人所填列資料刊登，如有不實，由候選人自行負責。"
        ],
        "180 772 247 858": [
            "里別 號次"
        ],
        "249 772 321 858": [

        ],
        "323 772 502 858": [
            "相　片 姓　名"
        ],
        "504 772 712 858": [

        ],
        "714 772 797 858": [
            "出生年",
            "月日"
        ],
        "799 772 865 858": [
            "性別 出生地"
        ],
        "867 772 967 858": [

        ],
        "969 772 1125 858": [
            "推薦之",
            "政　黨"
        ],
        "1127 772 1466 858": [
            "學　歷 經　歷 政　見"
        ],
        "1468 772 1854 858": [

        ],
        "1856 772 3037 858": [

        ],
        "180 863 247 1509": [
            "立",
            "泰",
            "里"
        ],
        "249 863 321 1076": [
            "1"
        ],
        "323 863 502 1076": [

        ],
        "504 863 712 1076": [
            "楊淑美"
        ],
        "714 863 797 1076": [
            "48",
            "年",
            "12",
            "月",
            "2",
            "日"
        ],
        "799 863 865 1076": [
            "女"
        ],
        "867 863 967 1076": [
            "臺灣省",
            "苗栗縣"
        ],
        "969 863 1125 1076": [
            "中國國民黨"
        ],
        "1127 863 1466 1076": [
            "1. 苗栗縣竹南鎮竹南國小畢業。",
            "2. 苗栗縣竹南鎮竹南國中畢業。",
            "3. 苗栗縣頭份鎮私立大成高級",
            "綜合商業科畢業。"
        ],
        "1468 863 1854 1076": [
            "1. 民國 65 年參加中華民國珠心算選",
            "手合格檢定。2. 民國 68 年任職 ( 現 )",
            "立泰里 289 巷銓億紡織廠品管會計。",
            "3. 民國 70 年任職苗栗縣竹南小兒科",
            "診所護理員。4.71 年結婚後定居立泰",
            "里自營經商舊貨五金業 30 餘年。5. 前",
            "臺北縣敬老協會志工 30 餘年。"
        ],
        "1856 863 3037 1076": [
            "1. 新人新政勤服務，提升全方位里民服務。2. 發心照顧弱勢婦幼老少，努力爭取婦幼老少福利。3. 關懷里內認真向學學生，",
            "發放獎學金。4. 定期道路、社區、水溝、清潔與消毒。5. 不定期舉辦里民聯誼各項文康活動，社區里民自強活動，與鄰",
            "長各項知性文化研習活動。6. 爭取發放老人津貼。7. 輔導里民提升就業機會。8. 不定期舉辦里民健康研習講座，提升里",
            "民健康保健常識。9. 頒發清寒獎助學金。10. 十大保證找得到人，深耕立泰里，傾聽基層里民心聲，為里民服務，促進爭",
            "取立泰里建設與詳和立泰里。全里民來督促里長全方位新政服務。"
        ],
        "249 1078 321 1294": [
            "2"
        ],
        "323 1078 502 1294": [

        ],
        "504 1078 712 1294": [
            "許文章"
        ],
        "714 1078 797 1294": [
            "45",
            "年",
            "8",
            "月",
            "1",
            "日"
        ],
        "799 1078 865 1294": [
            "男 臺中市 無"
        ],
        "867 1078 967 1294": [

        ],
        "969 1078 1125 1294": [

        ],
        "1127 1078 1466 1294": [
            "一東海高中電子科畢業"
        ],
        "1468 1078 1854 1294": [
            "一現任里長二國防部軍管區司令部後幹",
            "班 286 期結業三新莊區後備軍人輔導中",
            "心輔導組長四新莊區體育會民俗體育委",
            "員會主委五新莊區健行休閒協會創辦人",
            "六榮獲國防部後備軍人優秀輔導幹部獎",
            "七榮獲新莊市好人好事表揚八榮獲新莊",
            "市模範父親表揚九榮獲市政府五星級獎"
        ],
        "1856 1078 3037 1294": [
            "感謝各位鄉親四年前的熱情支持與牽成，文章得以有服務的機會，以穩健務實專職專業隨時找到人，熱心為鄉親全方位服務，三年多來不忘鄉親託負全心全力爭取建設創新福利繳交亮麗成績",
            "單。一經全力爭取 F208 免費公車自 8 月 18 日已正式開始行駛本里路線。二立泰里里民活動中心市政府已核准同意於高架橋下 P38 號橋柱位置興建已完成設計招標中即將發包動工。三成立環",
            "保志工隊維護里內環境清潔。四成立黃金里資收站資源回收物換專用垃圾袋服務。五關懷銀髮族開辦老人共餐活動。六運用資源回收回饋金開辦成績優秀奬學金。七運用資源回饋金辦理急難",
            "救助歲末關懷及公益研習活動。八運用醫療資源定期辦理免費健康檢查及保健諮詢。九協助弱勢及中低收入戶辦理各項福利救助申請。十開辦免費電腦教學及各項學習成長班。十一完成高架",
            "橋下興建籃球場提供里民休閒運動。十二完成高架橋下及周邊空間劃設汽機車停車格增加停車位。十三完成立泰公園親子遊樂設施及健身運動器具。十四開闢完成新泰路 381 巷與 369 巷巷道",
            "暢通並加裝路燈，讓學童及里民行走安全與便利。十五建置完成 321 巷沉水馬達自動抽水排放，解除淹水之苦。十六新泰路 347 巷口完成建置交通號誌燈及劃設行人穿越道，改善行人及汽車",
            "出入安全。十七拆除 357 巷口視線障礙，改善車輛出入安全順暢。十八 381 巷 401 巷 413 巷底至新泰路段沿線種植花木，綠美化環境並鋪設步道、裝置公園椅、運動器具提供里民運動休憩好地方。"
        ],
        "249 1296 321 1509": [
            "3"
        ],
        "323 1296 502 1509": [

        ],
        "504 1296 712 1509": [
            "林永清"
        ],
        "714 1296 797 1509": [
            "48",
            "年",
            "10",
            "月",
            "1",
            "日"
        ],
        "799 1296 865 1509": [
            "男"
        ],
        "867 1296 967 1509": [
            "臺灣省",
            "雲林縣"
        ],
        "969 1296 1125 1509": [
            "民主進步黨"
        ],
        "1127 1296 1466 1509": [
            "雲林縣西螺國中",
            "臺北縣立海山高中附設進修學校"
        ],
        "1468 1296 1854 1509": [
            "新莊區區政諮詢委員、新莊區調解委",
            "員、新莊市市民代表、新莊區雲林同鄉",
            "會副會長、新北市義勇消防總隊顧問、",
            "臺北縣治安協防大隊大隊長、新北市",
            "青少年關懷協會榮譽理事長、新北市",
            "休閒健行協會顧問、林口長庚醫院志",
            "工。國立臺北大學公共政策研習班"
        ],
        "1856 1296 3037 1509": [
            "一、維護里內治安、爭取監視系統增設。二、本里長期以來自來水混濁度均超過標準、嚴重影響水質、將要求自來水公司",
            "全面檢查改善、定期檢測、以維護里民用水安全。三、黃金資收站、將基金專款專用、財務透明、不淪為酬庸、用於里內",
            "建設或急難救助等公益用途。四、照顧銀髮族、成立銀髮族俱樂部、落實共餐、健康問診。五、爭取規劃新泰國中設立地",
            "下停車場、解決里民停車問題。六、妥善規劃里民活動中心、讓里民有活動休閒等空間。七、成立環保福利社推出環保用",
            "品等團購活動、結合環保局、廠商、讓里民做環保的同時、也能節省荷包。八、台 65 線高架道路及平面中環路、穿越本里、",
            "車速過快、飊車、交通流量大、噪音嚴重影響二旁里民生活品質、將爭取多設立測速照相及警方加強取諦、有效嚇阻飊車",
            "並降低速限、將噪音降至最低以解決噪音問題。九、協助本里立案之公寓大廈管理委員會、爭取節能減碳之補助金。"
        ],
        "180 1514 247 1944": [
            "中",
            "原",
            "里"
        ],
        "249 1514 321 1728": [
            "1"
        ],
        "323 1514 502 1728": [

        ],
        "504 1514 712 1728": [
            "趙勇成"
        ],
        "714 1514 797 1728": [
            "40",
            "年",
            "12",
            "月",
            "9",
            "日"
        ],
        "799 1514 865 1728": [
            "男 臺北市 無"
        ],
        "867 1514 967 1728": [

        ],
        "969 1514 1125 1728": [

        ],
        "1127 1514 1466 1728": [
            "臺北市龍山國小畢業",
            "新北市新莊區恆毅中學畢業"
        ],
        "1468 1514 1854 1728": [
            "中原里第五六七屆里長",
            "中原獅子會創會會長",
            "中原消防隊義消分隊長八年",
            "中平派出所民防分隊長四年",
            "新莊分局民防中隊中隊長"
        ],
        "1856 1514 3037 1728": [
            "1. 結合本區不分藍綠市議員提案，遷移中港消防隊至中央路行政區，新建像樣大樓，並爭取 10 樓以上大型雲梯車進駐，",
            "確保高樓住戶生命財產安全，歸還本里住宅區寧靜生活。2. 現有消防隊大樓建議改為本里圖書館暨托老托幼中心。3. 協",
            "助本里每棟大樓社區爭取相關福利及設施，如高壓多功能器材車（滅火、清洗、噴霧消毒等多用途）。4. 恢復原有巡守",
            "隊及強化監視器，並加強五樓公寓社區死角安全。5. 推動本里銀髮族保險與慶生活動。6. 推動本里巷道清潔維護。7. 推",
            "動本里路燈更換 LED燈具，強化亮度減少損壞。8. 每年舉辦中秋晚會聯絡感情。9. 洽詢本里鄰近廠商，提供里民就業機會。　",
            "　　有能力肯服務的里長勝過…，請鄉親全力支持趙勇成。"
        ],
        "249 1730 321 1944": [
            "2"
        ],
        "323 1730 502 1944": [

        ],
        "504 1730 712 1944": [
            "蘇文華"
        ],
        "714 1730 797 1944": [
            "52",
            "年",
            "4",
            "月",
            "10",
            "日"
        ],
        "799 1730 865 1944": [
            "男 新北市 無"
        ],
        "867 1730 967 1944": [

        ],
        "969 1730 1125 1944": [

        ],
        "1127 1730 1466 1944": [
            "東海高中肄業"
        ],
        "1468 1730 1854 1944": [
            "現任：新北市新莊區第一屆中原里　里",
            "長、中平派出所警友站　站長、新莊中",
            "港福德宮　委員、新莊三元玉虛宮　副",
            "主任委員、新莊後備憲兵新泰組、副組",
            "長、銀河系有限公司　負責人。",
            "曾任：中信國小第七、八屆家長會長、",
            "四季健行會　理事。"
        ],
        "1856 1730 3037 1944": [
            "一、建議公車客運公司以行政院第二辦公室為中心，以行經中港路、中平路、中原路為主，並多設站牌方便里民出入。",
            "二、建議市府速建電影文化中心及周邊公共設施提昇本里人文氣息的居家環境生活品質，為優良模範社區。",
            "三、督促機場捷運線早日通車，使里民有更便捷的交通，帶動里內繁榮。",
            "四、捷運站周邊多規劃汽機車停車位，可大大減低一般住宅社區周邊汽機車亂停問題。",
            "五、社區綠化及美化，消除髒亂並不定期消毒，以保持本里環境整潔。"
        ],
        "180 1949 247 2378": [
            "中",
            "平",
            "里"
        ],
        "249 1949 321 2162": [
            "1"
        ],
        "323 1949 502 2162": [

        ],
        "504 1949 712 2162": [
            "鞏台興"
        ],
        "714 1949 797 2162": [
            "54",
            "年",
            "8",
            "月",
            "7",
            "日"
        ],
        "799 1949 865 2162": [
            "男 臺北市 中國國民黨"
        ],
        "867 1949 967 2162": [

        ],
        "969 1949 1125 2162": [

        ],
        "1127 1949 1466 2162": [
            "新北市三重區穀保高工畢業"
        ],
        "1468 1949 1854 2162": [
            "1 臺北縣新莊市中平里第七、八屆里長",
            "2 新北市新莊區中平里第一屆里長",
            "3 新莊市中港區民防分隊顧問",
            "4 臺北縣警察之友支會 56 組副組長",
            "5 透視報導臺北分社顧問",
            "6 新莊區中平國中副會長"
        ],
        "1856 1949 3037 2162": [
            "里內持續性工作辦理與執行：1 將持續增設里內照明設備及消防設備。2 增設巷道照明設備。3 定期疏通水溝及排洪系統。",
            "4 定期里內環境消毒工作。5 主動關懷弱勢、低收入戶並協助申請各項福利及補助，特別針對高風險家庭主動追蹤與關懷。",
            "6 里內各巷道柏油路面鋪設工程。7 舉辦各項旅遊促進里內聯誼活動。8 安排里內大型廢棄物清運保潔里內環境衛生。9",
            "里內各社區管理委員會之間輔助調解平台。",
            "對里內未來遠景及發展方向：1 爭取公車路線便利交通方便里民。2 爭取辦理里民學習成長各項活動增進里民間情感交流。",
            "3 積極爭取中平里里內美化及綠化補助。4 積極爭取里內燈光照明穩定加強。5 里內交通及車輛停放管理規劃。6 建設中",
            "平服務不分晝夜，提升中平優質生活環境、竭心盡力打造全新的中平。"
        ],
        "249 2164 321 2378": [
            "2"
        ],
        "323 2164 502 2378": [

        ],
        "504 2164 712 2378": [
            "兵宗憲"
        ],
        "714 2164 797 2378": [
            "49",
            "年",
            "6",
            "月",
            "11",
            "日"
        ],
        "799 2164 865 2378": [
            "男 高雄市 無"
        ],
        "867 2164 967 2378": [

        ],
        "969 2164 1125 2378": [

        ],
        "1127 2164 1466 2378": [
            "高雄大榮高工畢業"
        ],
        "1468 2164 1854 2378": [
            "合承水電行 98 年度選為導護商店。",
            "甲乙種電匠資格。特定瓦斯器具裝修",
            "合格。合承水電行負責人。兩屆鄰長。",
            "擔任一道彩虹第 15  屆主任委員、中",
            "平國中家長會委員、榮富國小家長會",
            "委員。陸軍領導士官班。"
        ],
        "1856 2164 3037 2378": [
            "一、爭取電線電纜地下化；規劃汽機車停車位；種植路樹美化社區。　　　　　　五、爭取交通更便捷如公車路線增加、捷運接駁與延伸至本里，",
            "二、增加老人與婦幼福利；設立高中以下獎學金。協辦清寒、　　　　　　　　　　　使里民通勤更為便利。　　　　　　　　　　　　　　　　　　　　",
            "　　中低收入戶弱勢家庭與獨居老人之補助。　　　　　　　　　　　　　　　　六、加強滅火器增設及換藥並定期邀請消防單位至里內舉辦消防安全講習，",
            "三、舉辦低價高品質旅遊、元宵、中秋及聖誕聯歡晚會。　　　　　　　　　　　　　以維護里民生命財產安全。",
            "四、建立里內連線網路、社區之間治安聯防，將里內事務透明化，並與各社區　　七、健全里內義工組織、將里內環境打造成為模範里。",
            "　　管委會積極互動，以提昇里辦公室之事務功能及社區安全維護之效果。　　　八、全面宣導節能減碳，從日常生活中做到節能減碳，使中平里成為低碳里。"
        ],
        "180 2383 247 2812": [
            "立",
            "德",
            "里"
        ],
        "249 2383 321 2596": [
            "1"
        ],
        "323 2383 502 2596": [

        ],
        "504 2383 712 2596": [
            "莊玉雲"
        ],
        "714 2383 797 2596": [
            "48",
            "年",
            "8",
            "月",
            "18",
            "日"
        ],
        "799 2383 865 2596": [
            "女"
        ],
        "867 2383 967 2596": [
            "臺灣省",
            "嘉義縣"
        ],
        "969 2383 1125 2596": [
            "無"
        ],
        "1127 2383 1466 2596": [
            "板橋海山高中肄業"
        ],
        "1468 2383 1854 2596": [
            "新北市新莊區立德里第一屆里長",
            "新泰國小導護志工第二屆隊長",
            "中港第一社區發展協會常務理事",
            "臺北縣新莊市立德里第 5678 屆里長夫",
            "人"
        ],
        "1856 2383 3037 2596": [
            "一、全心全力，熱心為民服務，爭取建設與好福利。",
            "二、提升里民生活品質，定期消毒及不定期疏通水溝。",
            "三、增設滅火器及定期保養換藥維護里民生命財產安全。",
            "四、關懷里內中低收入戶及獨居老人，積極協助並尋求社福單位補助。",
            "五、配合勞工局，協助弱勢家庭與失業人士，尋求就業機會並積極幫助婦女二度就業。",
            "六、建請警政單位，加強夜間巡邏保障婦女行的安全。",
            "七、定期舉辦里民聯誼活動，促進里民連絡感情。",
            "八、廣納里民建言，以利推動里政進步。",
            "九、爭取國民運動中心，定期開放運動教室無收費給立德里民使用。"
        ],
        "249 2598 321 2812": [
            "2"
        ],
        "323 2598 502 2812": [

        ],
        "504 2598 712 2812": [
            "詹德盛"
        ],
        "714 2598 797 2812": [
            "34",
            "年",
            "12",
            "月",
            "3",
            "日"
        ],
        "799 2598 865 2812": [
            "男"
        ],
        "867 2598 967 2812": [
            "臺灣省",
            "苗栗縣"
        ],
        "969 2598 1125 2812": [
            "無"
        ],
        "1127 2598 1466 2812": [
            "初中。"
        ],
        "1468 2598 1854 2812": [
            "一、後備軍人，小組長。　",
            "二、臺北縣詹姓宗親會，分會長，監",
            "事。　",
            "三、太平洋電纜員工。　",
            "四、德昇機械企業社負責人。　",
            "五、臺北縣詹姓宗親會，分會長，監",
            "事。"
        ],
        "1856 2598 3037 2812": [
            "一、為確保里民，居家安全及防護。　",
            "二、建議政府，定期維護及保養，全里監視系統。　",
            "三、爭取轄區內，各公共設施，讓里民享有優惠之福利。　",
            "四、定期查視里內之環境衛生，水溝設施疏通清理消毒工作，絕不做有頭沒尾的事。　",
            "五、做稱職的里長，協助里民解決問題。　",
            "六、身心力行，推動各項工作里民提出我來做，以創造全里民更美好的生活空間和福利。"
        ],
        "180 2817 247 3246": [
            "立",
            "言",
            "里"
        ],
        "249 2817 321 3031": [
            "1"
        ],
        "323 2817 502 3031": [

        ],
        "504 2817 712 3031": [
            "呂淵源"
        ],
        "714 2817 797 3031": [
            "42",
            "年",
            "10",
            "月",
            "4",
            "日"
        ],
        "799 2817 865 3031": [
            "男 臺南市 無"
        ],
        "867 2817 967 3031": [

        ],
        "969 2817 1125 3031": [

        ],
        "1127 2817 1466 3031": [
            "後璧區菁寮國小",
            "新營區興國初中",
            "新北市立海山高中畢業"
        ],
        "1468 2817 1854 3031": [
            "1 新莊區紳士協會志工",
            "2 慈濟功德會資深會員",
            "3 温馨助人協會志工",
            "4 立言里巡守隊",
            "5 新泰華城社區委員",
            "6 百合協會理事",
            "7 陸軍兵工學校士官畢業"
        ],
        "1856 2817 3037 3031": [
            "1、主動關懷弱勢、低收入戶並協助申請各項福利。",
            "2、全力爭取國小、國中附設幼稚園增班，以利幼兒入學及教育補助。",
            "3、協助活化社區發展提升里民生活品質及每年舉辦中秋節聯誼活動。",
            "4、推動婦幼安全與緊急協助及設置立言里中、小學生獎助學金。",
            "5、提倡里民正當休閒活動：舉辦知性之旅及文康活動，增進里民情感交流。",
            "6、重視美化環境衛生、推動環保共識大家一起來努力維護，讓全里內整潔好視覺。",
            "7、對於里內各項經費之運用，秉持公平、公正、公開之原則，讓里民有知的權利。"
        ],
        "249 3033 321 3246": [
            "2"
        ],
        "323 3033 502 3246": [

        ],
        "504 3033 712 3246": [
            "劉進益"
        ],
        "714 3033 797 3246": [
            "45",
            "年",
            "2",
            "月",
            "14",
            "日"
        ],
        "799 3033 865 3246": [
            "男"
        ],
        "867 3033 967 3246": [
            "臺灣省",
            "花蓮縣"
        ],
        "969 3033 1125 3246": [
            "無"
        ],
        "1127 3033 1466 3246": [
            "一宜蘭縣蘇澳國中、國小畢業。",
            "二省立蘇澳高級水產職業學校畢",
            "業。"
        ],
        "1468 3033 1854 3246": [
            "一現任新北市第一屆新莊區立言里專",
            "業里長（獲新北市 101 年度特優里",
            "長表揚）。",
            "二歷任臺北縣第七、八屆專業里長。",
            "三立言里巡守隊隊長。",
            "四新泰華城社區第十二屆主任委員。",
            "五慈濟環保志工。"
        ],
        "1856 3033 3037 3246": [
            "1 爭取新建新泰國小地下停車場一案，已獲市政府正面回覆。若能當選連任，定將竭盡所能將其實現，以徹底解決立言",
            "里停車位不足的問題。（中環路緊臨國小後門 10 米綠帶明年將採市地重劃，優先徵收）2 強力要求市政府將本里之有線",
            "電視及寬頻光纖電纜地下化。除了能美化市容外，也能避免現有系統台壟斷，讓其他業者公平競爭，進而降低里民的收",
            "視費用。3 嚴格監督里內之新建住宅工程，避免因施工造成噪音擾鄰、交通不便及居家不安；並要求建商在施工前展開",
            "與臨近住戶之溝通與協調。4 督促新海瓦斯公司與台電公司，依表定時間檢查管線，落實維修保養以確保用戶安全。5 依",
            "市政府都市更新相關法令，全程協助里內老舊住宅之「重建、整建、維護、改造」。6 極力要求公車業者增加行經新泰",
            "路至新莊捷運站的班次；促成公車業者以小型巴士提供行經新泰路至新莊捷運站的區間車，讓里民搭捷運更便利。"
        ],
        "180 3251 247 3463": [
            "中",
            "宏",
            "里"
        ],
        "249 3251 321 3463": [
            "1"
        ],
        "323 3251 502 3463": [

        ],
        "504 3251 712 3463": [
            "洪少欽"
        ],
        "714 3251 797 3463": [
            "41",
            "年",
            "7",
            "月",
            "12",
            "日"
        ],
        "799 3251 865 3463": [
            "男"
        ],
        "867 3251 967 3463": [
            "臺灣省",
            "彰化縣"
        ],
        "969 3251 1125 3463": [
            "無"
        ],
        "1127 3251 1466 3463": [
            "國小畢業。"
        ],
        "1468 3251 1854 3463": [
            "中宏里現任里長、新莊區里長聯誼會",
            "中港區常委、現任里長主席、新莊市",
            "第 6、7、8 屆中宏里里長、93 年榮獲",
            "內政部特優里長、臺北縣義消總隊顧",
            "問、中平派出所警友站顧問、中原消",
            "防隊義消顧問、中港第二社區理事。"
        ],
        "1856 3251 3037 3463": [
            "1、定期做好對里內老人聯誼身體健檢諮詢、殘障、婦幼弱勢團體愛心關懷。",
            "2、建請警政單位里內廣設監視系統，以維護治安，加強警察巡邏，以保障里民生命財產安全。",
            "3、里內優秀學童獎助學金每年定期發放，嘉惠學子上進鼓勵之學習認真 ‧",
            "4、定期疏浚排水溝、社區環境消毒綠美化、滅火器增購新品及換葯。",
            "5、協助里民辦理各種社會福利補助申請，高風險家庭的關懷。",
            "6、里內一劉支線及中誠街 166 巷底水利溝環境綠美化設施再提升，使成為里民最佳休憩場所。",
            "7、定期舉辦各項文康公益活動，促進里民聯誼交流 ‧"
        ],
        "180 3468 247 3681": [
            "立",
            "志",
            "里"
        ],
        "249 3468 321 3681": [
            "1"
        ],
        "323 3468 502 3681": [

        ],
        "504 3468 712 3681": [
            "陳崑祥"
        ],
        "714 3468 797 3681": [
            "32",
            "年",
            "8",
            "月",
            "23",
            "日"
        ],
        "799 3468 865 3681": [
            "男"
        ],
        "867 3468 967 3681": [
            "臺灣省",
            "雲林縣"
        ],
        "969 3468 1125 3681": [
            "無"
        ],
        "1127 3468 1466 3681": [
            "雲林縣西螺國小畢業",
            "雲林縣西螺鎮西螺初級中學肄業"
        ],
        "1468 3468 1854 3681": [
            "1. 現任立志里里長　",
            "2.",
            "新莊市第 5、6、7、8 屆及新莊區第 1 屆立志里里長",
            "　",
            "3.",
            "96 年獲得模範里長、績優里長及特優里長三冠表揚",
            "　",
            "4. 76 年好人好事代表　",
            "5. 臺北縣雲林同鄉會總會常務監事",
            "6. 中港國小導護志工"
        ],
        "1856 3468 3037 3681": [
            "阿永仔來自雲林，生根立志。感謝立志鄉親多年來對永仔的支持與肯定，永仔何德何能無以回報疼惜永仔的每一份情。面對各位鄉親、好友們的愛護",
            "及對立志濃厚的情誼及使命感，實在不捨辜負大家的期許。這次參選，永仔除了秉持最初的熱誠為大家服務，更會將大家託負永仔的使命一一完成。",
            "懇請大家繼續支持、疼惜永仔。1. 新莊心、立志情，堅持用心做好每一件事。2. 重視治安爭取全里加強警力巡邏，維護鄉親身家安全。3. 協助低收、",
            "身障、單親等弱勢族群申請社會補助，並於每年年底，可直接至里辦公處辦理複查。4. 主動關懷高風險家庭，讓立志的孩子們都能平安、快樂的成長。",
            "5. 專業辦公處採開放空間，提供里民閱報、飲水、休憩聯誼好去處。6. 美化環境衛生，推動環保共識，每日隨時巡視里內巷弄，遇有髒亂點，馬上清理。",
            "7. 加強防治登革熱，注意環境消毒及宣導正確防疫知識。8. 滅火器定期檢修、換藥，確保里民居家財產安全。9. 每年舉辦里鄰活動，促進里民情誼交流，",
            "以達敦親睦鄰、守望相助目的，凝聚鄉親情。10. 里民需求優先，實現政見為要，經驗務必累積，專職、專業的里長，一人當選全家服務。"
        ],
        "180 3686 247 3898": [
            "立",
            "功",
            "里"
        ],
        "249 3686 321 3898": [
            "1"
        ],
        "323 3686 502 3898": [

        ],
        "504 3686 712 3898": [
            "陳易澤"
        ],
        "714 3686 797 3898": [
            "64",
            "年",
            "3",
            "月",
            "31",
            "日"
        ],
        "799 3686 865 3898": [
            "男 新北市 無"
        ],
        "867 3686 967 3898": [

        ],
        "969 3686 1125 3898": [

        ],
        "1127 3686 1466 3898": [
            "一、澳洲南澳大學科技管理研究",
            "所碩士畢業",
            "二、中國文化大學政治學系研究",
            "所碩士畢業"
        ],
        "1468 3686 1854 3898": [
            "一、國立政治大學法律研究所二、榮獲臺",
            "北縣十大傑出青年三、新莊市調解委員",
            "四、中港國小家長會會長五、陳謝美玉代",
            "表服務處主任六、103 年新北市特優里長",
            "七、新莊區第一屆立功里里長八、新北地",
            "方法院調解委員九、新北地檢司法修復促",
            "進者十、連續 9 年調委行政院長獎"
        ],
        "1856 3686 3037 3898": [
            "服務基層回饋心　　　　　 建設鄉里感恩情",
            "一、建設政見兌現：1、里內街道監視器與滅火器架設完成 2、里內定期環境清潔與排水溝清理消毒 3、 里內環保志工與守望相助隊成立 4、 里內透明壓克力公佈欄增設完成 5、",
            "里內公車站牌增設立功里名稱　二、藝文政見兌現：1、定期召開立功里里民大會，廣納民意 2、定期舉辦元宵節、中秋節民俗活動 3、頒發立功里國中小學成績優良獎學金",
            "4、完成里內中老年長者電腦成長班教學　三、服務政見兌現：1、 定期舉辦里內里民健康檢查活動 2、協辦清寒、低收入戶等家庭申請補助 3、協助 65 歲長者，國民年金申",
            "請辦理 4、協助里內勞工各項勞健保補助申請 5、協助各項稅務申報與提供節稅資訊 6、成立溫馨關懷小組協助急難及弱勢者 7、調解里民糾紛，提供法律見解分析 8、協辦食、",
            "衣、住、行、育樂相關證件 9、定期舉辦里內里民就業徵才活動　四、里內未來展望：1、延續里內建設、藝文、服務政見推行 2、增設里內綠色植物的種植與街道綠化 3、",
            "架設里內社區網站，以利連結各機關 4、定期舉辦急救、防災、緊急應變演習 5、協助里民完成租屋補助申請手續"
        ],
        "180 3903 247 4115": [
            "立",
            "基",
            "里"
        ],
        "249 3903 321 4115": [
            "1"
        ],
        "323 3903 502 4115": [

        ],
        "504 3903 712 4115": [
            "張中貞"
        ],
        "714 3903 797 4115": [
            "46",
            "年",
            "11",
            "月",
            "24",
            "日"
        ],
        "799 3903 865 4115": [
            "女 臺北市 無"
        ],
        "867 3903 967 4115": [

        ],
        "969 3903 1125 4115": [

        ],
        "1127 3903 1466 4115": [
            "●",
            "金甌女中",
            "●",
            "臺北商專附設空中補校－企業",
            "管理科畢業"
        ],
        "1468 3903 1854 4115": [
            "●",
            "新北市新莊區導護志工協會創會總",
            "幹事（81 年）",
            "●",
            "中港國小／新泰國中志工（79 年至今）",
            "●",
            "新北地檢署榮譽觀護人（85 年至今）",
            "●",
            "新莊市立基里第八屆里長",
            "●",
            "新莊區立基里第一屆里長"
        ],
        "1856 3903 3037 4115": [
            "＂新北市好立基＂感謝大家的支持與努力，我們做到了！中貞期許好還要更好，要繼續創新幸福美好立基里。感謝鄉親八年來，對中貞一路相挺。給我服務鄉親",
            "的機會，一個讓我有回饋鄉里的機會。中貞報以專業全職負責任的服務態度，一心一意不忘「立基好生活」的目標。",
            "　　萬分感謝鄉親和無怨無悔志工的支持與協助，讓我們所參加的競賽都能榮獲佳績。更感謝公所、各級民意代表的相挺相助，爭取的各項建設，都能一一順利",
            "完成 ‧ 現在立基里整個脫胎換骨，煥然一新，是令人稱羨的好所在。本里於 100 年榮獲消防局遴選為防災、救災示範里。",
            "　　102 年新北市績優守望相助隊，榮獲＂特優＂獎今年參加新北市里環境競賽，榮獲最高榮譽－「五星級」認證。這份榮譽中貞不敢自居自滿，這是所有立基",
            "鄉親給我機會，共同努力的成果。我們不能因此自滿，應繼續努力建設不能停頓，共創幸福美滿～好立基是我們的目標。敬愛的鄉親父老好朋友們：請繼續鞭策",
            "中貞，支持立基里，懇請再給中貞服務機會，中貞必定用感恩回饋之心來服務。讓立基里更溫馨、更亮麗，立基有您真好！中貞以立基為榮！"
        ],
        "180 4120 247 4329": [
            "立",
            "廷",
            "里"
        ],
        "249 4120 321 4329": [
            "1"
        ],
        "323 4120 502 4329": [

        ],
        "504 4120 712 4329": [
            "許任銘"
        ],
        "714 4120 797 4329": [
            "67",
            "年",
            "4",
            "月",
            "22",
            "日"
        ],
        "799 4120 865 4329": [
            "男"
        ],
        "867 4120 967 4329": [
            "臺灣省",
            "彰化縣"
        ],
        "969 4120 1125 4329": [
            "無"
        ],
        "1127 4120 1466 4329": [

        ],
        "1468 4120 1854 4329": [
            "一、大中美國際保全股份有限公司 -",
            "負責人。",
            "二、中英公寓大廈管理維護股份有限",
            "公司－負責人。",
            "三、新莊區中平派出所警友站顧問。"
        ],
        "1856 4120 3037 4329": [
            "一、每年發放獎助學金，鼓勵里內子弟上進。",
            "二、規劃立廷里資訊網路平台建設，讓政令宣導、里務推展、活動訊息等公開、快速、方便。",
            "三、聯繫各相關醫療院所，安排每年一～二次定期健康檢查，做好里民健康照護。",
            "四、提升創意文化生活規劃，由里內各社區依特性分別辦理音樂、游泳、茶藝、烹飪、插花、電腦等之研習及講座。",
            "五、加強照顧里內弱勢及獨居老人。年節致贈平安米或禮物等，做好關懷及慰問。",
            "六、規劃並爭取歐洲村全區內巷道裝置 LED 路燈及路口交通號誌燈，以維護里內婦女及小孩行的安全。"
        ]
    }
}