{
    "1": {
        "105 212 2983 481": [
            "彰化縣溪州鄉第十七屆鄉長選舉",
            "第二十屆鄉民代表會第一、四選區、第二十屆村長選舉"
        ],
        "105 482 2983 626": [
            "臺灣省彰化縣溪州鄉第十七屆鄉長選舉、第二十屆鄉民代表會第一、四選區選舉、第二十屆村長選舉，經定於中華民國103年11月29日(星期六)上午8時起至下午4時止舉行投票。",
            "茲依公職人員選舉罷免法第四十七條規定，將候選人所填之政見及個人資料刊登如下，候選人個人資料係依據候選人所填列資料刊登，如有不實，由候選人自行負責。"
        ],
        "105 635 1539 727": [
            "臺灣省彰化縣溪州鄉民代表會第二十屆代表選舉第一選舉區候選人："
        ],
        "1548 635 2983 727": [
            "臺灣省彰化縣溪州鄉第二十屆村長選舉候選人："
        ],
        "105 728 177 856": [

        ],
        "178 728 234 856": [

        ],
        "235 728 432 856": [

        ],
        "433 728 489 856": [

        ],
        "490 728 546 856": [

        ],
        "547 728 602 856": [

        ],
        "603 728 659 856": [

        ],
        "660 728 716 856": [

        ],
        "717 728 829 856": [

        ],
        "830 728 1016 856": [

        ],
        "1017 728 1539 856": [

        ],
        "1548 728 1622 856": [

        ],
        "1623 728 1679 856": [

        ],
        "1680 728 1877 856": [

        ],
        "1879 728 1934 856": [

        ],
        "1935 728 1991 856": [

        ],
        "1992 728 2048 856": [

        ],
        "2049 728 2104 856": [

        ],
        "2105 728 2161 856": [

        ],
        "2162 728 2274 856": [

        ],
        "2275 728 2461 856": [

        ],
        "2463 728 2983 856": [

        ],
        "105 858 177 3404": [
            "ˉˉˉ  ˉ",
            "ˉˉ ˉ ˉ",
            "ˉˉ  ˉˉ ˉˉ  ˉˉ"
        ],
        "178 858 234 1282": [
            "1"
        ],
        "235 858 432 1282": [

        ],
        "433 858 489 1282": [

        ],
        "490 858 546 1282": [
            "54",
            "年",
            "02",
            "月",
            "12",
            "日"
        ],
        "547 858 602 1282": [

        ],
        "603 858 659 1282": [

        ],
        "660 858 716 1282": [

        ],
        "717 858 829 1282": [
            "彰化縣立溪",
            "州國小。彰",
            "化縣立溪州",
            "國中。國立",
            "員林高中"
        ],
        "830 858 1016 1282": [
            "１．前立法委員邱創",
            "進（第五屆）服務處",
            "助理。２．前立法委",
            "員邱創進（第六屆）",
            "服務處副主任。３．",
            "前彰化縣議員黃振彥",
            "服務處主任。４．溪",
            "州鄉公所秘書（鄉長",
            "黃盛祿）。５．彰化",
            "市公所市政顧問（市",
            "長邱建富）。６．彰",
            "化縣小英之友會副秘",
            "書長。"
        ],
        "1017 858 1539 1282": [
            "１．做鄉民的助理，熱誠服務。",
            "２．堅持台灣民主，落實基層。",
            "３．促進溪州繁榮，活絡商機。",
            "４．協助溪州鄉政，爭取建設。",
            "５．守護母親之河，愛鄉愛土。"
        ],
        "1548 858 1622 1278": [
            ""
        ],
        "1623 858 1679 1278": [
            "1"
        ],
        "1680 858 1877 1278": [

        ],
        "1879 858 1934 1278": [

        ],
        "1935 858 1991 1278": [
            "40",
            "年",
            "11",
            "月",
            "1",
            "日"
        ],
        "1992 858 2048 1278": [

        ],
        "2049 858 2104 1278": [

        ],
        "2105 858 2161 1278": [

        ],
        "2162 858 2274 1278": [
            "國小畢業"
        ],
        "2275 858 2461 1278": [
            "溪州鄉坑厝村第１６",
            "、１７、１８、１９",
            "屆村長"
        ],
        "2463 858 2983 1278": [
            "一、加強本村建設。",
            "二、推動美化村里環境。",
            "三、關懷照顧年邁長者。",
            "四、爭取本村各項福利。"
        ],
        "178 1283 234 1707": [
            "2"
        ],
        "235 1283 432 1707": [

        ],
        "433 1283 489 1707": [

        ],
        "490 1283 546 1707": [
            "57",
            "年",
            "09",
            "月",
            "15",
            "日"
        ],
        "547 1283 602 1707": [

        ],
        "603 1283 659 1707": [

        ],
        "660 1283 716 1707": [

        ],
        "717 1283 829 1707": [
            "南州國小、",
            "溪州國中、",
            "大成商工"
        ],
        "830 1283 1016 1707": [
            "１、溪州鄉義警顧問",
            "團顧問。２、南州國",
            "小家長委員。３、溪",
            "州鄉同心慈善會顧問",
            "。４、現任彰化縣傳",
            "統文化美食協會理事",
            "長。５、現任溪州鄉",
            "民代表。"
        ],
        "1017 1283 1539 1707": [
            "一、推動社會福利、落實為民服務。",
            "二、督促鄉公所輔導農民生產高經濟作物，增加農民收益。",
            "三、督促鄉公所完善地方公共設施，排水系統，道路交通等建設。",
            "四、善盡鄉代職責，為民喉舌，爭取敬老及弱勢婦幼福利，做好鄉公所和民",
            "　　眾良好溝通橋樑。"
        ],
        "1548 1287 1622 2128": [
            "ˉ",
            "ˉˉ"
        ],
        "1623 1287 1679 1707": [
            "1"
        ],
        "1680 1287 1877 1707": [

        ],
        "1879 1287 1934 1707": [

        ],
        "1935 1287 1991 1707": [
            "47",
            "年",
            "9",
            "月",
            "3",
            "日"
        ],
        "1992 1287 2048 1707": [

        ],
        "2049 1287 2104 1707": [

        ],
        "2105 1287 2161 1707": [

        ],
        "2162 1287 2274 1707": [
            "芙朝國小",
            "埤頭國中"
        ],
        "2275 1287 2461 1707": [

        ],
        "2463 1287 2983 1707": [
            "（一）促進社區發展協會功能，改善社區環境衛生及綠美化，提升生活品質",
            "　　　。",
            "（二）爭取經費，改善村內巷道和路柏油路面，增設公園涼亭，讓鄉親有好",
            "　　　的休閒場所。",
            "（三）關懷獨居單親老人及貧困低收入戶，主動爭取年節發放慰問金及協助",
            "　　　辦理各項補助。"
        ],
        "178 1708 234 2132": [
            "3"
        ],
        "235 1708 432 2132": [

        ],
        "433 1708 489 2132": [

        ],
        "490 1708 546 2132": [
            "58",
            "年",
            "6",
            "月",
            "24",
            "日"
        ],
        "547 1708 602 2132": [

        ],
        "603 1708 659 2132": [

        ],
        "660 1708 716 2132": [

        ],
        "717 1708 829 2132": [
            "溪州國民小",
            "學畢業、溪",
            "州國民中學",
            "畢業。"
        ],
        "830 1708 1016 2132": [
            "自家耕種農田、彰化",
            "秀水青商會、國際珠",
            "寶協會、溪州鄉同心",
            "慈善會。"
        ],
        "1017 1708 1539 2132": [
            "帶領溪州鄉邁向→安全→光明→進步；１．增設路口監視器。２．增設暗巷",
            "路燈、照明燈。３．協助弱勢申請補助。４．致力推動環保。５．綠化道路",
            "，藝術美化村莊。６．不定期剪除雜草、消毒環境。７．組織志工隊關懷獨",
            "居老人。"
        ],
        "1623 1708 1679 2128": [
            "2"
        ],
        "1680 1708 1877 2128": [

        ],
        "1879 1708 1934 2128": [

        ],
        "1935 1708 1991 2128": [
            "52",
            "年",
            "7",
            "月",
            "7",
            "日"
        ],
        "1992 1708 2048 2128": [

        ],
        "2049 1708 2104 2128": [

        ],
        "2105 1708 2161 2128": [

        ],
        "2162 1708 2274 2128": [
            "私立青年高",
            "級中學畢業"
        ],
        "2275 1708 2461 2128": [
            "溪州救國團→會長",
            "溪州婦女會→秘書",
            "溪州青溪婦女會→委",
            "員",
            "溪州衛生所→委員"
        ],
        "2463 1708 2983 2128": [
            "爭取村民救助及就業機會，爭取社區活動中心辦公室成立。"
        ],
        "178 2133 234 2557": [
            "4"
        ],
        "235 2133 432 2557": [

        ],
        "433 2133 489 2557": [

        ],
        "490 2133 546 2557": [
            "42",
            "年",
            "05",
            "月",
            "24",
            "日"
        ],
        "547 2133 602 2557": [

        ],
        "603 2133 659 2557": [

        ],
        "660 2133 716 2557": [

        ],
        "717 2133 829 2557": [
            "溪州初中肄",
            "業"
        ],
        "830 2133 1016 2557": [
            "１、復興宮管理委員",
            "會顧問。２、溪州老",
            "人會顧問。３、溪州",
            "義消、溪州警察之友",
            "會、溪州同心慈善會",
            "第７、８、１０屆顧",
            "問、第１１屆顧問團",
            "副團長。４、第１７",
            "、１８、１９屆鄉民",
            "代表。"
        ],
        "1017 2133 1539 2557": [
            "一、促請公所加強各項社會福利，照顧弱勢族群。",
            "二、監督各項公共工程建設，確保工程品質，造福鄉民。",
            "三、振興地方產業文化，促請公所確實規劃輔導，帶動經濟發展。",
            "四、發展地方農特產品，促請政府加強輔導協助，以增進農民收入，改善生",
            "　　活。"
        ],
        "1548 2137 1622 2979": [
            "ˉ",
            "ˉˉ"
        ],
        "1623 2137 1679 2557": [
            "1"
        ],
        "1680 2137 1877 2557": [

        ],
        "1879 2137 1934 2557": [

        ],
        "1935 2137 1991 2557": [
            "48",
            "年",
            "4",
            "月",
            "27",
            "日"
        ],
        "1992 2137 2048 2557": [

        ],
        "2049 2137 2104 2557": [

        ],
        "2105 2137 2161 2557": [

        ],
        "2162 2137 2274 2557": [
            "福興國中",
            "彰化高商"
        ],
        "2275 2137 2461 2557": [
            "一、和泰五金行",
            "二",
            "、",
            "現任佳泰五金建",
            "　　材行負責人",
            "三",
            "、",
            "溪州社區發展協",
            "　　會理事長"
        ],
        "2463 2137 2983 2557": [
            "彩色的人生，逐夢的理想，藉由理事長這位小園丁，帶領村民們一同努力來",
            "創造，一位不計較也不比較，懷著一顆赤誠服務的心，不紙上談兵，腳踏實",
            "地，實事求是，展現兔子腳的勤快，為村民爭取更多的社會福利與建設。",
            "搭起友誼之橋，懇託村民的支持，給予不計較，認真付出的我，名正言順的",
            "認證，共同舞出快樂的人生，美麗的家園。"
        ],
        "178 2558 234 2982": [
            "5"
        ],
        "235 2558 432 2982": [

        ],
        "433 2558 489 2982": [

        ],
        "490 2558 546 2982": [
            "54",
            "年",
            "9",
            "月",
            "5",
            "日"
        ],
        "547 2558 602 2982": [

        ],
        "603 2558 659 2982": [

        ],
        "660 2558 716 2982": [

        ],
        "717 2558 829 2982": [
            "高職肄業"
        ],
        "830 2558 1016 2982": [
            "中華盆花協會（馬拉",
            "巴栗協會執行委員）",
            "溪州鄉農會會員代表",
            "溪州鄉第一選區巡守",
            "隊顧問團副團長",
            "溪州國中家長會常務",
            "委員",
            "溪州分駐所民防義警",
            "顧問"
        ],
        "1017 2558 1539 2982": [
            "全力爭取建設",
            "全方位服務",
            "關懷弱勢"
        ],
        "1623 2558 1679 2979": [
            "2"
        ],
        "1680 2558 1877 2979": [

        ],
        "1879 2558 1934 2979": [

        ],
        "1935 2558 1991 2979": [
            "30",
            "年",
            "09",
            "月",
            "25",
            "日"
        ],
        "1992 2558 2048 2979": [

        ],
        "2049 2558 2104 2979": [

        ],
        "2105 2558 2161 2979": [

        ],
        "2162 2558 2274 2979": [
            "溪州國民小",
            "學畢業。"
        ],
        "2275 2558 2461 2979": [
            "溪州村第十五屆、十",
            "六屆、十七屆、十八",
            "屆、十九屆村長"
        ],
        "2463 2558 2983 2979": [
            "一、關懷弱勢團體及獨居老人。",
            "二、向公所及上級機關爭取基層建設。",
            "三、爭取村民各項社會福利。",
            "四、續作村民與各機關溝通橋樑。",
            "五、傾聽民意，隨時服務村民。"
        ],
        "178 2984 234 3404": [
            "6"
        ],
        "235 2984 432 3404": [

        ],
        "433 2984 489 3404": [

        ],
        "490 2984 546 3404": [
            "46",
            "年",
            "7",
            "月",
            "9",
            "日"
        ],
        "547 2984 602 3404": [

        ],
        "603 2984 659 3404": [

        ],
        "660 2984 716 3404": [

        ],
        "717 2984 829 3404": [

        ],
        "830 2984 1016 3404": [
            "私立淵明國中教師、",
            "十信工商教師、雲林",
            "工專教師、私立環球",
            "商專教師、南州國小",
            "家長會長、茂育電腦",
            "工程師"
        ],
        "1017 2984 1539 3404": [
            "改變溪州由基層，基層的改變決定溪州未來，還溪州公園正名（費茲洛改回",
            "溪州公園）"
        ],
        "1548 2987 1622 3829": [
            "ˉ",
            "ˉˉ"
        ],
        "1623 2987 1679 3408": [
            "1"
        ],
        "1680 2987 1877 3408": [

        ],
        "1879 2987 1934 3408": [

        ],
        "1935 2987 1991 3408": [
            "39",
            "年",
            "12",
            "月",
            "28",
            "日"
        ],
        "1992 2987 2048 3408": [

        ],
        "2049 2987 2104 3408": [

        ],
        "2105 2987 2161 3408": [

        ],
        "2162 2987 2274 3408": [
            "高中"
        ],
        "2275 2987 2461 3408": [
            "南州國小常委顧問。",
            "同心慈善會永久會員",
            "。后天宮、復興宮委",
            "員。尾厝社區發展協",
            "會召集人。溪州義警",
            "及警友會顧問。彰化",
            "國際同濟會Ｂ區輔導",
            "長。溪州衛生所志工",
            "主委。彰化縣劉氏宗",
            "親會創會長。現任尾",
            "厝村村長。"
        ],
        "2463 2987 2983 3408": [
            "１、為鄉為民，全力以赴。２、一人做，二人全方位服務。３、關心獨居老",
            "人及弱勢家庭。４、努力爭取經費，改善尾厝村環境。５、協助村民辦理申",
            "請各項補助。６、時時刻刻傾聽民意，使尾厝村更團結、更和諧。"
        ],
        "1623 3409 1679 3829": [
            "2"
        ],
        "1680 3409 1877 3829": [

        ],
        "1879 3409 1934 3829": [

        ],
        "1935 3409 1991 3829": [
            "49",
            "年",
            "1",
            "月",
            "31",
            "日"
        ],
        "1992 3409 2048 3829": [

        ],
        "2049 3409 2104 3829": [

        ],
        "2105 3409 2161 3829": [

        ],
        "2162 3409 2274 3829": [
            "專科畢業"
        ],
        "2275 3409 2461 3829": [
            "１、８７、８８年度",
            "溪州國小家長會長。",
            "２、８８～９９年復",
            "興宮常務監事。３、",
            "９０年第十四、十六",
            "屆縣農會代表。４、",
            "９４年溪州農會第十",
            "五屆理事。５、９４",
            "年溪州鄉同心慈善會",
            "會長。６、現任縣警",
            "察局北斗分局中隊長",
            "。７、福興汽車保養",
            "廠董事長。"
        ],
        "2463 3409 2983 3829": [
            "一、爭取徵收村內未開闢之計畫道路開通及舖設經費。",
            "二、現有農家路鄰國小路段水溝加蓋工程（保留住戶原建物）。",
            "三、爭取溪州國小農家路段圍牆退縮２公尺及綠化、美化，提升道路使用人",
            "　　之便利及行車安全。",
            "四、爭取土地公廟廢棄鐵道完成舖設柏油路段至莒光路口。",
            "五、１４鄰舜耕路至文化路全線路段擴建完工。",
            "六、由中山路轉中通路至復興宮路旁水溝加蓋工程（保留住戶原建物）。",
            "七、改善公所路及光明街排水系統工程。",
            "八、提供２４小時急難救助專線服務電話：０９１０－４９７７７６。",
            "九、每學期贊助溪州國小義工媽媽。",
            "十、獎勵尾厝村義工福利。",
            "十一、籌募各方善信及優良廠商，所得經費補助村內弱勢及低收入戶。",
            "十二、每月乙次村內環境整理及雜草噴灑除草劑。"
        ],
        "105 3412 1539 3505": [
            "臺灣省彰化縣溪州鄉第二十屆村長選舉候選人："
        ],
        "105 3506 177 3634": [

        ],
        "178 3506 234 3634": [

        ],
        "235 3506 432 3634": [

        ],
        "433 3506 489 3634": [

        ],
        "490 3506 546 3634": [

        ],
        "547 3506 602 3634": [

        ],
        "603 3506 659 3634": [

        ],
        "660 3506 716 3634": [

        ],
        "717 3506 829 3634": [

        ],
        "830 3506 1016 3634": [

        ],
        "1017 3506 1539 3634": [

        ],
        "105 3636 177 4056": [
            ""
        ],
        "178 3636 234 4056": [
            "1"
        ],
        "235 3636 432 4056": [

        ],
        "433 3636 489 4056": [

        ],
        "490 3636 546 4056": [
            "40",
            "年",
            "11",
            "月",
            "8",
            "日"
        ],
        "547 3636 602 4056": [

        ],
        "603 3636 659 4056": [

        ],
        "660 3636 716 4056": [

        ],
        "717 3636 829 4056": [
            "僑義國小畢",
            "業"
        ],
        "830 3636 1016 4056": [
            "壽南宮總務委員民國",
            "１０２年擔任壽南宮",
            "主委、目前兼溪厝社",
            "區理事長、第十八屆",
            "十九屆村長。"
        ],
        "1017 3636 1539 4056": [
            "１、主動發覺村內需要、隨時反映民意。",
            "２、誠信、用心、盡責、勤走與鄉親互動溝通、建設地方。",
            "３、提升服務效率、服務村民為優先、村內軟硬設施維護。",
            "４、美化居家環境、提升村民生活品質。",
            "５、關懷老人及弱勢族群。",
            "６、加強推行祥和社會工作、村民感情良性互動，端正社會風氣。"
        ],
        "1548 3838 2983 4252": [
            "菜公村、三條村、三圳村、水尾村",
            "東州村、舊眉村、圳寮村",
            "第 3 選舉區應有婦女當選名額1名",
            "選舉區別",
            "第 1 選舉區",
            "3",
            "2",
            "4",
            "第 2 選舉區",
            "第 4 選舉區",
            "西畔村、柑園村、成功村、大庄村、",
            "榮光村、潮洋村、張厝村",
            "2",
            "第 3 選舉區",
            "備  註",
            "所 轄 村 里 名 稱 應選出名額",
            "溪厝村、坑厝村、瓦厝村、溪州村、",
            "尾厝村",
            "溪州鄉民代表選舉之選舉區劃分及應選出名額"
        ],
        "105 4064 1539 4252": [
            "選前受賄不是福，賄選人士必貪污。"
        ]
    }
}